{
  "category": {
    "id": "kinozal_movies_ru",
    "title": "Наше кино"
  },
  "page": 5,
  "limit": 20,
  "total": 262,
  "items": [
    {
      "adult": false,
      "backdrop_path": "/nihm4vHpe5Y7XmbnjAFp4zJ3tRT.jpg",
      "genre_ids": [
        18,
        10749,
        10752
      ],
      "id": 204166,
      "original_language": "ru",
      "original_title": "Звездопад",
      "overview": "Они встретились и полюбили друг друга в прифронтовом городе. Шла война, которая диктовала свои законы, не оставлявшие места для любви. Да и мать девушки была против женитьбы: ведь если он погибнет, что станет с ее единственной дочерью? И герой решает расстаться с любимой навсегда…",
      "popularity": 0.9758,
      "poster_path": "/rotqCzpgTXvlNb6W4uryRphpWYU.jpg",
      "release_date": "1981-12-16",
      "title": "Звездопад",
      "video": false,
      "vote_average": 3.4,
      "vote_count": 7,
      "belongs_to_collection": null,
      "budget": 0,
      "genres": [
        {
          "id": 18,
          "name": "драма"
        },
        {
          "id": 10749,
          "name": "мелодрама"
        },
        {
          "id": 10752,
          "name": "военный"
        }
      ],
      "homepage": "",
      "imdb_id": "tt0083145",
      "origin_country": [
        "SU"
      ],
      "production_companies": [
        {
          "id": 344,
          "logo_path": "/xenuUvcunUNpbaDOYGhWZERaym7.png",
          "name": "Mosfilm",
          "origin_country": "SU"
        }
      ],
      "production_countries": [
        {
          "iso_3166_1": "SU",
          "name": "Soviet Union"
        }
      ],
      "revenue": 0,
      "runtime": 92,
      "spoken_languages": [
        {
          "english_name": "Russian",
          "iso_639_1": "ru",
          "name": "Pусский"
        }
      ],
      "status": "Released",
      "tagline": "",
      "release_quality": "",
      "media_type": "movie",
      "categories": [
        "kinozal_movies_ru"
      ]
    },
    {
      "adult": false,
      "backdrop_path": "/ooxxA6N48002tM3R40o7xOujtse.jpg",
      "genre_ids": [
        35
      ],
      "id": 110807,
      "original_language": "ru",
      "original_title": "Не ждали, не гадали",
      "overview": "В обычную советскую квартиру, где живёт и ссорится обычная советская семья внезапно вламывается… осёл. Все попытки изгнать скотину кончаются безрезультатно. Не могут помочь ни милиция, ни ветеринарная служба, ни даже местный хулиган-алкаш Коселков. И только вездесущим киношникам, которым понадобилось животное для съёмок, удается усыпить и удалить осла из квартиры. В борьбе с житейской неурядицей семейные связи восстанавливаются и укрепляются. Хотя в одной соседней квартире, где живёт такая же обычная советская семья разгорается такая же обычная ссора. И тогда снова приходит он…",
      "popularity": 0.8902,
      "poster_path": "/9SttPpEUaQQeGQAOQsm9Ep3pxmZ.jpg",
      "release_date": "1982-06-06",
      "title": "Не ждали, не гадали",
      "video": false,
      "vote_average": 0,
      "vote_count": 0,
      "belongs_to_collection": null,
      "budget": 0,
      "genres": [
        {
          "id": 35,
          "name": "комедия"
        }
      ],
      "homepage": "",
      "imdb_id": "tt0251894",
      "origin_country": [
        "SU"
      ],
      "production_companies": [
        {
          "id": 6608,
          "logo_path": "/eALlDyTQSw5rLU1IJvYps4himcU.png",
          "name": "Ekran",
          "origin_country": "SU"
        }
      ],
      "production_countries": [
        {
          "iso_3166_1": "SU",
          "name": "Soviet Union"
        }
      ],
      "revenue": 0,
      "runtime": 77,
      "spoken_languages": [
        {
          "english_name": "Russian",
          "iso_639_1": "ru",
          "name": "Pусский"
        }
      ],
      "status": "Released",
      "tagline": "",
      "release_quality": "1080p",
      "media_type": "movie",
      "categories": [
        "kinozal_movies_ru"
      ]
    },
    {
      "adult": false,
      "backdrop_path": "/5NT6ngOQRRJ5OtIUcvK9bqyQgaf.jpg",
      "genre_ids": [
        10751,
        14,
        12
      ],
      "id": 167858,
      "original_language": "ru",
      "original_title": "Сказка странствий",
      "overview": "Жили-были двое бездомных сирот. Маленький Май обладал необыкновенным даром находить спрятанное золото. Однажды в рождественскую ночь злой и жадный Горгон, переодевшись Дедом Морозом, украл мальчика. И тогда Марта отправилась на поиски брата. В этом нелёгком пути её сопровождал весёлый и добрый друг Орландо — врач, поэт, философ, путешественник. Пока Марта искала брата, Май превратился в жадного и черствого человека. Но терпение, любовь, надежда и новый друг помогли девочке воскресить его душу.",
      "popularity": 0.898,
      "poster_path": "/qbtWz2qjxThJGPMyld0uqTkSY4M.jpg",
      "release_date": "1983-09-05",
      "title": "Сказка странствий",
      "video": false,
      "vote_average": 6,
      "vote_count": 26,
      "belongs_to_collection": null,
      "budget": 0,
      "genres": [
        {
          "id": 10751,
          "name": "семейный"
        },
        {
          "id": 14,
          "name": "фэнтези"
        },
        {
          "id": 12,
          "name": "приключения"
        }
      ],
      "homepage": "",
      "imdb_id": "tt0141830",
      "origin_country": [
        "SU"
      ],
      "production_companies": [
        {
          "id": 1931,
          "logo_path": "/5erHhgvym2cTORao8ajtn2gbiTH.png",
          "name": "Filmové studio Barrandov",
          "origin_country": "XC"
        },
        {
          "id": 7168,
          "logo_path": null,
          "name": "România Film",
          "origin_country": "RO"
        },
        {
          "id": 344,
          "logo_path": "/xenuUvcunUNpbaDOYGhWZERaym7.png",
          "name": "Mosfilm",
          "origin_country": "SU"
        }
      ],
      "production_countries": [
        {
          "iso_3166_1": "XC",
          "name": "Czechoslovakia"
        },
        {
          "iso_3166_1": "RO",
          "name": "Romania"
        },
        {
          "iso_3166_1": "SU",
          "name": "Soviet Union"
        }
      ],
      "revenue": 0,
      "runtime": 101,
      "spoken_languages": [
        {
          "english_name": "Russian",
          "iso_639_1": "ru",
          "name": "Pусский"
        }
      ],
      "status": "Released",
      "tagline": "",
      "release_quality": "",
      "media_type": "movie",
      "categories": [
        "kinozal_movies_ru"
      ]
    },
    {
      "adult": false,
      "backdrop_path": "/9hvjK6wKS5z0KApZFl1Z3Z0jU6X.jpg",
      "genre_ids": [
        14,
        878,
        18
      ],
      "id": 137209,
      "original_language": "ru",
      "original_title": "Гибель сенсации",
      "overview": "Ученый-идеалист создает роботов для облегчения труда рабочих, а в результате гибнет, растоптанный своими созданиями, которых «перепрограммировали» в карателей забастовщиков...",
      "popularity": 0.6065,
      "poster_path": "/tu2YVUAq8zGYXDygam7wnCAXsCj.jpg",
      "release_date": "1935-04-17",
      "title": "Гибель сенсации",
      "video": false,
      "vote_average": 4.4,
      "vote_count": 7,
      "belongs_to_collection": null,
      "budget": 0,
      "genres": [
        {
          "id": 14,
          "name": "фэнтези"
        },
        {
          "id": 878,
          "name": "фантастика"
        },
        {
          "id": 18,
          "name": "драма"
        }
      ],
      "homepage": "",
      "imdb_id": "tt0240539",
      "origin_country": [
        "SU"
      ],
      "production_companies": [
        {
          "id": 8970,
          "logo_path": null,
          "name": "Mezhrabpomfilm",
          "origin_country": "SU"
        }
      ],
      "production_countries": [
        {
          "iso_3166_1": "SU",
          "name": "Soviet Union"
        }
      ],
      "revenue": 0,
      "runtime": 85,
      "spoken_languages": [
        {
          "english_name": "Russian",
          "iso_639_1": "ru",
          "name": "Pусский"
        }
      ],
      "status": "Released",
      "tagline": "",
      "release_quality": "1080p",
      "media_type": "movie",
      "categories": [
        "kinozal_movies_ru"
      ]
    },
    {
      "adult": false,
      "backdrop_path": "/kV2lB7z3ZHTjOJFyDEeUpJzlrTc.jpg",
      "genre_ids": [
        35
      ],
      "id": 536466,
      "original_language": "ru",
      "original_title": "Повод",
      "overview": "Идет товарищеский суд. Домашний кот Адам обвиняется в воровстве колбасы из магазина, утят из колхозной птицефермы и многих других прегрешениях, которые списывают на беднягу буквально все жители села…",
      "popularity": 0.8682,
      "poster_path": "/hiXoSPHiZk7PyI12Cg5STkXHJxW.jpg",
      "release_date": "1986-01-01",
      "title": "Повод",
      "video": false,
      "vote_average": 6,
      "vote_count": 1,
      "belongs_to_collection": null,
      "budget": 0,
      "genres": [
        {
          "id": 35,
          "name": "комедия"
        }
      ],
      "homepage": "",
      "imdb_id": "tt2708610",
      "origin_country": [
        "SU"
      ],
      "production_companies": [
        {
          "id": 3161,
          "logo_path": "/p22GDJaOniIWidl1vPqzBv4qxFN.png",
          "name": "Odessa Film Studio",
          "origin_country": "SU"
        },
        {
          "id": 14620,
          "logo_path": "/zbQk1aw57z6LUOSQzb0MoZDLiUz.png",
          "name": "Gosteleradio USSR",
          "origin_country": "SU"
        }
      ],
      "production_countries": [
        {
          "iso_3166_1": "SU",
          "name": "Soviet Union"
        }
      ],
      "revenue": 0,
      "runtime": 127,
      "spoken_languages": [
        {
          "english_name": "Russian",
          "iso_639_1": "ru",
          "name": "Pусский"
        }
      ],
      "status": "Released",
      "tagline": "",
      "release_quality": "1080p",
      "media_type": "movie",
      "categories": [
        "kinozal_movies_ru"
      ]
    },
    {
      "adult": false,
      "backdrop_path": "/iMDtp5bhrNUe7PaeloNSpPvWR0t.jpg",
      "genre_ids": [
        878,
        35,
        14
      ],
      "id": 65080,
      "original_language": "ru",
      "original_title": "Эта веселая планета",
      "overview": "Прилетевшие на Землю инопланетяне попадают на встречу Нового года в обычный Дворец культуры. Столкнувшись со множеством загадок, они постепенно приходят к пониманию того, что земная жизнь без шутки и смеха, без искусства и любви невозможна.",
      "popularity": 0.9472,
      "poster_path": "/9E5xhcvA0vJT1Q3w7C1EasTu04H.jpg",
      "release_date": "1973-12-31",
      "title": "Эта весёлая планета",
      "video": false,
      "vote_average": 5,
      "vote_count": 11,
      "belongs_to_collection": null,
      "budget": 0,
      "genres": [
        {
          "id": 878,
          "name": "фантастика"
        },
        {
          "id": 35,
          "name": "комедия"
        },
        {
          "id": 14,
          "name": "фэнтези"
        }
      ],
      "homepage": "",
      "imdb_id": "tt0070042",
      "origin_country": [
        "SU"
      ],
      "production_companies": [
        {
          "id": 344,
          "logo_path": "/xenuUvcunUNpbaDOYGhWZERaym7.png",
          "name": "Mosfilm",
          "origin_country": "SU"
        }
      ],
      "production_countries": [
        {
          "iso_3166_1": "SU",
          "name": "Soviet Union"
        }
      ],
      "revenue": 0,
      "runtime": 94,
      "spoken_languages": [
        {
          "english_name": "Russian",
          "iso_639_1": "ru",
          "name": "Pусский"
        }
      ],
      "status": "Released",
      "tagline": "",
      "release_quality": "",
      "media_type": "movie",
      "categories": [
        "kinozal_movies_ru"
      ]
    },
    {
      "adult": false,
      "backdrop_path": "/mm3aNTjFvuo0jeitneRDc1ZUNjI.jpg",
      "genre_ids": [
        18,
        878,
        9648
      ],
      "id": 593,
      "original_language": "ru",
      "original_title": "Солярис",
      "overview": "На космическую станцию, сотрудники которой давно и тщетно пытаются сладить с загадкой планеты Солярис, покрытой Океаном, прибывает новый обитатель, психолог Крис Кельвин, чтобы разобраться в странных сообщениях, поступающих со станции, и «закрыть» ее вместе со всей бесплодной «соляристикой». Поначалу ему кажется, что немногие уцелевшие на станции ученые сошли с ума. Потом он и сам становится жертвой жуткого наваждения: ему является его бывшая возлюбленная Хари, некогда на земле покончившая с собой.",
      "popularity": 3.5758,
      "poster_path": "/xYN3dwytiL3vgcuynzYitIcKmKS.jpg",
      "release_date": "1972-03-20",
      "title": "Солярис",
      "video": false,
      "vote_average": 7.788,
      "vote_count": 1755,
      "belongs_to_collection": null,
      "budget": 0,
      "genres": [
        {
          "id": 18,
          "name": "драма"
        },
        {
          "id": 878,
          "name": "фантастика"
        },
        {
          "id": 9648,
          "name": "детектив"
        }
      ],
      "homepage": "",
      "imdb_id": "tt0069293",
      "origin_country": [
        "SU"
      ],
      "production_companies": [
        {
          "id": 77883,
          "logo_path": null,
          "name": "Unit Four",
          "origin_country": ""
        },
        {
          "id": 77882,
          "logo_path": null,
          "name": "Creative Unit of Writers & Cinema Workers",
          "origin_country": ""
        },
        {
          "id": 344,
          "logo_path": "/xenuUvcunUNpbaDOYGhWZERaym7.png",
          "name": "Mosfilm",
          "origin_country": "SU"
        }
      ],
      "production_countries": [
        {
          "iso_3166_1": "SU",
          "name": "Soviet Union"
        }
      ],
      "revenue": 0,
      "runtime": 169,
      "spoken_languages": [
        {
          "english_name": "Russian",
          "iso_639_1": "ru",
          "name": "Pусский"
        }
      ],
      "status": "Released",
      "tagline": "",
      "release_quality": "2160p",
      "media_type": "movie",
      "categories": [
        "kinozal_movies_ru"
      ]
    },
    {
      "adult": false,
      "backdrop_path": null,
      "genre_ids": [
        18
      ],
      "id": 386816,
      "original_language": "ru",
      "original_title": "Пастух и царь",
      "overview": "Художественная биография Ивана, начавшего жизнь пастухом и ставшего орденоносцем и красным командиром (1904-1934 гг.).",
      "popularity": 0.5569,
      "poster_path": "/2HmKqo2FsVYc6HpY1B8SaiHHRb9.jpg",
      "release_date": "1935-03-24",
      "title": "Пастух и царь",
      "video": false,
      "vote_average": 9,
      "vote_count": 1,
      "belongs_to_collection": null,
      "budget": 0,
      "genres": [
        {
          "id": 18,
          "name": "драма"
        }
      ],
      "homepage": "",
      "imdb_id": null,
      "origin_country": [
        "SU"
      ],
      "production_companies": [
        {
          "id": 8970,
          "logo_path": null,
          "name": "Mezhrabpomfilm",
          "origin_country": "SU"
        }
      ],
      "production_countries": [
        {
          "iso_3166_1": "SU",
          "name": "Soviet Union"
        }
      ],
      "revenue": 0,
      "runtime": 72,
      "spoken_languages": [
        {
          "english_name": "Russian",
          "iso_639_1": "ru",
          "name": "Pусский"
        }
      ],
      "status": "Released",
      "tagline": "",
      "release_quality": "1080p",
      "media_type": "movie",
      "categories": [
        "kinozal_movies_ru"
      ]
    },
    {
      "adult": false,
      "backdrop_path": null,
      "genre_ids": [
        18,
        36
      ],
      "id": 336781,
      "original_language": "ru",
      "original_title": "Лермонтов",
      "overview": "Действие картины начинается с предсмертных дней Пушкина и заканчивается гибелью Лермонтова. Страдающий, радостно-взволнованный, одухотворенный, мятежный — таким предстает перед зрителями великий русский поэт в гениальных строчках его стихов, в глубоких размышлениях, в смелых и дерзких поступках.",
      "popularity": 0.2807,
      "poster_path": "/58FboxFm0KKEz3fmJd4rHwcpTIq.jpg",
      "release_date": "1943-07-07",
      "title": "Лермонтов",
      "video": false,
      "vote_average": 6.1,
      "vote_count": 4,
      "belongs_to_collection": null,
      "budget": 0,
      "genres": [
        {
          "id": 18,
          "name": "драма"
        },
        {
          "id": 36,
          "name": "история"
        }
      ],
      "homepage": "",
      "imdb_id": "tt0037015",
      "origin_country": [
        "SU"
      ],
      "production_companies": [
        {
          "id": 15444,
          "logo_path": "/pdfT1FpxrxjsWnVEJ88XpyBmc1I.png",
          "name": "Soyuzdetfilm",
          "origin_country": "SU"
        },
        {
          "id": 52478,
          "logo_path": null,
          "name": "Stalinabad Film Studio",
          "origin_country": "SU"
        }
      ],
      "production_countries": [
        {
          "iso_3166_1": "SU",
          "name": "Soviet Union"
        }
      ],
      "revenue": 0,
      "runtime": 76,
      "spoken_languages": [
        {
          "english_name": "Russian",
          "iso_639_1": "ru",
          "name": "Pусский"
        }
      ],
      "status": "Released",
      "tagline": "",
      "release_quality": "",
      "media_type": "movie",
      "categories": [
        "kinozal_movies_ru"
      ]
    },
    {
      "adult": false,
      "backdrop_path": "/aTs8uEWvxm8ej1f1NgMizp8CaK9.jpg",
      "genre_ids": [
        35
      ],
      "id": 79847,
      "original_language": "ru",
      "original_title": "Алло, Варшава!",
      "overview": "Врач Анджей Вишневский становится победителем конкурса, проводимого польским телевидением. Сам Анджей родился на Украине, а в годы Второй мировой войны, еще будучи ребенком, оказался в Польше. Герой знакомится с журналисткой Ренатой, которая соглашается помочь ему найти сестру в СССР. Поиски родственницы завершаются успешно, а Рената и Анджей становятся мужем и женой.",
      "popularity": 0.4479,
      "poster_path": "/7L7OLPqawBf2g0vSnqB7IUpIqXJ.jpg",
      "release_date": "1971-01-01",
      "title": "Алло, Варшава!",
      "video": false,
      "vote_average": 3,
      "vote_count": 1,
      "belongs_to_collection": null,
      "budget": 0,
      "genres": [
        {
          "id": 35,
          "name": "комедия"
        }
      ],
      "homepage": "",
      "imdb_id": "tt1407930",
      "origin_country": [
        "SU"
      ],
      "production_companies": [
        {
          "id": 11436,
          "logo_path": "/zvvXyn4CvHqmBX7X6zdbDOCGG3M.png",
          "name": "Sverdlovsk Film Studio",
          "origin_country": "SU"
        }
      ],
      "production_countries": [
        {
          "iso_3166_1": "SU",
          "name": "Soviet Union"
        }
      ],
      "revenue": 0,
      "runtime": 78,
      "spoken_languages": [
        {
          "english_name": "Russian",
          "iso_639_1": "ru",
          "name": "Pусский"
        }
      ],
      "status": "Released",
      "tagline": "",
      "release_quality": "",
      "media_type": "movie",
      "categories": [
        "kinozal_movies_ru"
      ]
    },
    {
      "adult": false,
      "backdrop_path": null,
      "genre_ids": [
        10752,
        18
      ],
      "id": 641126,
      "original_language": "ru",
      "original_title": "Сто солдат и две девушки",
      "overview": "Вторая мировая война. Героиня фильма — санинструктор Аля Буланина, общение с которой возрождает веру солдат в то, что дома их ждут и любят…",
      "popularity": 0.2324,
      "poster_path": "/ezYaaq8hbVQmvGHvN907pv8Q7Nk.jpg",
      "release_date": "1989-01-01",
      "title": "Сто солдат и две девушки",
      "video": false,
      "vote_average": 0,
      "vote_count": 0,
      "belongs_to_collection": null,
      "budget": 0,
      "genres": [
        {
          "id": 10752,
          "name": "военный"
        },
        {
          "id": 18,
          "name": "драма"
        }
      ],
      "homepage": "",
      "imdb_id": "tt3042438",
      "origin_country": [
        "SU"
      ],
      "production_companies": [
        {
          "id": 10845,
          "logo_path": "/8qh5BEyKYOQ0e81LPbvWHQvyOy5.png",
          "name": "Lenfilm",
          "origin_country": "SU"
        }
      ],
      "production_countries": [
        {
          "iso_3166_1": "SU",
          "name": "Soviet Union"
        }
      ],
      "revenue": 0,
      "runtime": 93,
      "spoken_languages": [
        {
          "english_name": "Russian",
          "iso_639_1": "ru",
          "name": "Pусский"
        }
      ],
      "status": "Released",
      "tagline": "",
      "release_quality": "",
      "media_type": "movie",
      "categories": [
        "kinozal_movies_ru"
      ]
    },
    {
      "adult": false,
      "backdrop_path": "/7n2aqnJBercfaj4M4q86dCsHtUT.jpg",
      "genre_ids": [
        35,
        10749
      ],
      "id": 472950,
      "original_language": "ru",
      "original_title": "Центровой из поднебесья",
      "overview": "Музыкальная комедия о баскетбольной команде «Студент», которую возглавляет тренер Самсон Грозняк. Команда полна амбиций, но ей не хватает хорошего центрового. Юрий Кулич-Куликовский — обычный чабан, имеет блестящие природные данные для баскетбола, но спорт его совсем не интересует. Он бы никогда и не попал в команду, если бы не влюбился в певицу Нину Челнокову. Солистка популярного ансамбля с гастролями посещает множество городов, и единственный шанс поспеть за ней — объездить страну вместе с баскетбольной командой. Постепенно тренеру удаётся пробудить в Юрии спортивное честолюбие. Пройдя через череду поражений и побед, команда «Студент» выходит в финал престижного соревнования, где им предстоит помериться силами с американскими баскетболистами. Встреча становится звёздным часом для Юрия…",
      "popularity": 0.7195,
      "poster_path": "/7fBuzDDsv4D3ReourIGF0YY9MzG.jpg",
      "release_date": "1975-12-28",
      "title": "Центровой из поднебесья",
      "video": false,
      "vote_average": 5,
      "vote_count": 2,
      "belongs_to_collection": null,
      "budget": 0,
      "genres": [
        {
          "id": 35,
          "name": "комедия"
        },
        {
          "id": 10749,
          "name": "мелодрама"
        }
      ],
      "homepage": "",
      "imdb_id": "tt0175259",
      "origin_country": [
        "SU"
      ],
      "production_companies": [
        {
          "id": 21978,
          "logo_path": "/3EP1gJYMGlEt7j17naPMg5e2LH2.png",
          "name": "Gorky Film Studios",
          "origin_country": "SU"
        }
      ],
      "production_countries": [
        {
          "iso_3166_1": "SU",
          "name": "Soviet Union"
        }
      ],
      "revenue": 0,
      "runtime": 95,
      "spoken_languages": [
        {
          "english_name": "Russian",
          "iso_639_1": "ru",
          "name": "Pусский"
        }
      ],
      "status": "Released",
      "tagline": "",
      "release_quality": "",
      "media_type": "movie",
      "categories": [
        "kinozal_movies_ru"
      ]
    },
    {
      "adult": false,
      "backdrop_path": "/igmncZ3e94AqFuvK8rojxgsKbe1.jpg",
      "genre_ids": [
        35
      ],
      "id": 376836,
      "original_language": "ru",
      "original_title": "Миргород и его обитатели",
      "overview": "Миргород, небольшой провинциальный город, живет размеренной тихой жизнью, погрузившись в атмосферу сна и покоя. Но все меняется с появлением Голопузя, большого авантюриста и проходимца, который решает увеличить свое состояние, используя местное население. С первых дней нахождения незваного гостя, в Миргороде начинают происходить различные мистические происшествия, которые кардинально меняют жизнь горожан, делая их очевидцами удивительных событий. Изменения в городском существовании не проходят мимо городничего, заинтересовавшегося ссорой двух давних друзей, за которой стоит Голопузь.",
      "popularity": 0.6853,
      "poster_path": "/zPPVPs5BEwu9M1POgBUMKdvubaL.jpg",
      "release_date": "1983-01-01",
      "title": "Миргород и его обитатели",
      "video": false,
      "vote_average": 6.6,
      "vote_count": 5,
      "belongs_to_collection": null,
      "budget": 0,
      "genres": [
        {
          "id": 35,
          "name": "комедия"
        }
      ],
      "homepage": "",
      "imdb_id": "tt0197685",
      "origin_country": [
        "SU"
      ],
      "production_companies": [
        {
          "id": 4581,
          "logo_path": "/p858ADU9O67a7ageVEjsk18jqak.png",
          "name": "Dovzhenko Film Studios",
          "origin_country": "SU"
        }
      ],
      "production_countries": [
        {
          "iso_3166_1": "SU",
          "name": "Soviet Union"
        }
      ],
      "revenue": 0,
      "runtime": 134,
      "spoken_languages": [
        {
          "english_name": "Russian",
          "iso_639_1": "ru",
          "name": "Pусский"
        }
      ],
      "status": "Released",
      "tagline": "",
      "release_quality": "1080p",
      "media_type": "movie",
      "categories": [
        "kinozal_movies_ru"
      ]
    },
    {
      "adult": false,
      "backdrop_path": "/ePwOHh2DfZHtUYvtnC3EMHrI9lj.jpg",
      "genre_ids": [
        35,
        10770
      ],
      "id": 72611,
      "original_language": "ru",
      "original_title": "Здравствуйте, я ваша тётя!",
      "overview": "Действие происходит в начале ХХ века. Безработный Бабс попадает в богатый дом, где вынужден, переодевшись в женскую одежду, сыграть роль тетушки-миллионерши, чтобы помочь двум юношам жениться на их возлюбленных...",
      "popularity": 0.9021,
      "poster_path": "/b0MK0IivTlGNzrvuuq8eTvOGtN8.jpg",
      "release_date": "1975-12-26",
      "title": "Здравствуйте, я ваша тётя!",
      "video": false,
      "vote_average": 7.127,
      "vote_count": 55,
      "belongs_to_collection": null,
      "budget": 0,
      "genres": [
        {
          "id": 35,
          "name": "комедия"
        },
        {
          "id": 10770,
          "name": "телевизионный фильм"
        }
      ],
      "homepage": "",
      "imdb_id": "tt0073927",
      "origin_country": [
        "SU"
      ],
      "production_companies": [
        {
          "id": 6608,
          "logo_path": "/eALlDyTQSw5rLU1IJvYps4himcU.png",
          "name": "Ekran",
          "origin_country": "SU"
        }
      ],
      "production_countries": [
        {
          "iso_3166_1": "SU",
          "name": "Soviet Union"
        }
      ],
      "revenue": 0,
      "runtime": 98,
      "spoken_languages": [
        {
          "english_name": "Russian",
          "iso_639_1": "ru",
          "name": "Pусский"
        }
      ],
      "status": "Released",
      "tagline": "По мотивам пьесы Б. Томаса «Тётка Чарлея»",
      "release_quality": "",
      "media_type": "movie",
      "categories": [
        "kinozal_movies_ru"
      ]
    },
    {
      "adult": false,
      "backdrop_path": null,
      "genre_ids": [
        18,
        10752
      ],
      "id": 658164,
      "original_language": "ru",
      "original_title": "Лесная баллада",
      "overview": "В первые дни войны у десятилетней девочки Айгуль, дочери советского офицера, погибает мать. Больную, измученную девочку прячут от фашистов старый мельник и его внук Федя. На глазах у детей немцы убивают деда, подозревая его в связях с партизанами. Дети остаются одни.  В поисках партизан фашисты ведут повальные обыски и при одном из них обнаруживают девочку–казашку. Ей грозит высылка в Германию в качестве экзотического сувенира - «азиаточки из России» для жены немца Фольмера. Феде с помощью односельчан удается выкрасть Айгуль. Но мужественная девочка выходит к немцам, так как отдан приказ вешать каждого шестого жителя. И в тот момент, когда каратели готовы были торжествовать, партизаны окружают площадь.",
      "popularity": 0.3429,
      "poster_path": "/qDvomM5HgLw1eVERKTcJJHpheNT.jpg",
      "release_date": "1972-12-25",
      "title": "Лесная баллада",
      "video": false,
      "vote_average": 8,
      "vote_count": 1,
      "belongs_to_collection": null,
      "budget": 0,
      "genres": [
        {
          "id": 18,
          "name": "драма"
        },
        {
          "id": 10752,
          "name": "военный"
        }
      ],
      "homepage": "",
      "imdb_id": "tt11497370",
      "origin_country": [
        "SU"
      ],
      "production_companies": [
        {
          "id": 232195,
          "logo_path": "/buy12sVmKaY1jiixLNCDZpc2MSo.png",
          "name": "Kazakhfilm",
          "origin_country": "SU"
        }
      ],
      "production_countries": [
        {
          "iso_3166_1": "SU",
          "name": "Soviet Union"
        }
      ],
      "revenue": 0,
      "runtime": 75,
      "spoken_languages": [
        {
          "english_name": "Russian",
          "iso_639_1": "ru",
          "name": "Pусский"
        }
      ],
      "status": "Released",
      "tagline": "",
      "release_quality": "2160p",
      "media_type": "movie",
      "categories": [
        "kinozal_movies_ru"
      ]
    },
    {
      "adult": false,
      "backdrop_path": null,
      "genre_ids": [
        18
      ],
      "id": 1274785,
      "original_language": "ru",
      "original_title": "Мой добрый человек",
      "overview": "По мотивам рассказа У.Назарова \"Дерзость\".",
      "popularity": 0.13,
      "poster_path": "/zfIj95y32PLNUQwK2Aa50ibkGqk.jpg",
      "release_date": "1973-01-01",
      "title": "Мой добрый человек",
      "video": false,
      "vote_average": 0,
      "vote_count": 0,
      "belongs_to_collection": null,
      "budget": 0,
      "genres": [
        {
          "id": 18,
          "name": "драма"
        }
      ],
      "homepage": "",
      "imdb_id": null,
      "origin_country": [
        "SU"
      ],
      "production_companies": [
        {
          "id": 189675,
          "logo_path": "/dcpUQhz4nFOiFFHEcr1TuhlznLM.png",
          "name": "Uzbekfilm",
          "origin_country": "SU"
        }
      ],
      "production_countries": [
        {
          "iso_3166_1": "SU",
          "name": "Soviet Union"
        }
      ],
      "revenue": 0,
      "runtime": 69,
      "spoken_languages": [
        {
          "english_name": "Russian",
          "iso_639_1": "ru",
          "name": "Pусский"
        }
      ],
      "status": "Released",
      "tagline": "",
      "release_quality": "",
      "media_type": "movie",
      "categories": [
        "kinozal_movies_ru"
      ]
    },
    {
      "adult": false,
      "backdrop_path": "/oC6SliTXSmCn2XDnNTOzQpi1o1X.jpg",
      "genre_ids": [
        35,
        10749
      ],
      "id": 63302,
      "original_language": "ru",
      "original_title": "Чокнутые",
      "overview": "Первая в России «чугунка» — железная дорога от Петербурга до Царского Села — была построена по инициативе австрийского инженера Герстнера. История умалчивает о том, какие почти фантастические события сопутствовали этому смелому предприятию.",
      "popularity": 1.0358,
      "poster_path": "/iqO6iaCNmXNNsbORfkINkP9iPAA.jpg",
      "release_date": "1991-06-06",
      "title": "Чокнутые",
      "video": false,
      "vote_average": 4.3,
      "vote_count": 10,
      "belongs_to_collection": null,
      "budget": 0,
      "genres": [
        {
          "id": 35,
          "name": "комедия"
        },
        {
          "id": 10749,
          "name": "мелодрама"
        }
      ],
      "homepage": "",
      "imdb_id": "tt0175529",
      "origin_country": [
        "SU"
      ],
      "production_companies": [
        {
          "id": 1859,
          "logo_path": null,
          "name": "Ritm",
          "origin_country": "SU"
        }
      ],
      "production_countries": [
        {
          "iso_3166_1": "SU",
          "name": "Soviet Union"
        }
      ],
      "revenue": 0,
      "runtime": 90,
      "spoken_languages": [
        {
          "english_name": "Russian",
          "iso_639_1": "ru",
          "name": "Pусский"
        }
      ],
      "status": "Released",
      "tagline": "",
      "release_quality": "",
      "media_type": "movie",
      "categories": [
        "kinozal_movies_ru"
      ]
    },
    {
      "adult": false,
      "backdrop_path": "/bsnA3Gnidfc7JUAo1QOoSk6a05j.jpg",
      "genre_ids": [
        18,
        10752
      ],
      "id": 67064,
      "original_language": "ru",
      "original_title": "Солдаты",
      "overview": "Июль 1942 года. Лейтенант Керженцев, его связной Валега и полковой разведчик Седых вместе с отступающими частями нашей армии идут мимо украинских деревень к Сталинграду, где уже формируются новые части… Фильм снят по повести Виктора Некрасова «В окопах Сталинграда»",
      "popularity": 0.7344,
      "poster_path": "/yTRU0p4UyIult5wUHIn71bdODim.jpg",
      "release_date": "1956-12-06",
      "title": "Солдаты",
      "video": false,
      "vote_average": 4.2,
      "vote_count": 6,
      "belongs_to_collection": null,
      "budget": 0,
      "genres": [
        {
          "id": 18,
          "name": "драма"
        },
        {
          "id": 10752,
          "name": "военный"
        }
      ],
      "homepage": "",
      "imdb_id": "tt0049776",
      "origin_country": [
        "SU"
      ],
      "production_companies": [
        {
          "id": 10845,
          "logo_path": "/8qh5BEyKYOQ0e81LPbvWHQvyOy5.png",
          "name": "Lenfilm",
          "origin_country": "SU"
        }
      ],
      "production_countries": [
        {
          "iso_3166_1": "SU",
          "name": "Soviet Union"
        }
      ],
      "revenue": 0,
      "runtime": 106,
      "spoken_languages": [
        {
          "english_name": "Russian",
          "iso_639_1": "ru",
          "name": "Pусский"
        }
      ],
      "status": "Released",
      "tagline": "",
      "release_quality": "",
      "media_type": "movie",
      "categories": [
        "kinozal_movies_ru"
      ]
    },
    {
      "adult": false,
      "backdrop_path": "/1kShjfoNZe0wTF16jvPaX8OOel1.jpg",
      "genre_ids": [
        10770,
        35,
        10749
      ],
      "id": 43430,
      "original_language": "ru",
      "original_title": "Ирония судьбы, или С легким паром!",
      "overview": "Лирическая комедия о том, как четверо друзей под Новый год, по традиции, отправились в баню… А получился один из лучших фильмов отечественного кино за всю его историю. Эльдару Рязанову удалось в этой картине все - от мягкой новогодней интонации до великолепного актерского ансамбля: Андрей Мягков (Женя), Барбара Брыльска (Надя), Юрий Яковлев (Ипполит), Александр Ширвиндт (Павел), Георгий Бурков (Миша)…",
      "popularity": 2.9226,
      "poster_path": "/b7hCjU6dgJBzXgbC5BUOcrCm9Zj.jpg",
      "release_date": "1975-12-31",
      "title": "Ирония судьбы, или С легким паром!",
      "video": false,
      "vote_average": 7.273,
      "vote_count": 251,
      "belongs_to_collection": {
        "id": 107473,
        "name": "Ирония судьбы (Коллекция)",
        "poster_path": "/1DzMfdobDqF67PhAtLiECqLbsqV.jpg",
        "backdrop_path": "/gI5Rr5fIzKhRsYDQYjFcttMCQU5.jpg"
      },
      "budget": 0,
      "genres": [
        {
          "id": 10770,
          "name": "телевизионный фильм"
        },
        {
          "id": 35,
          "name": "комедия"
        },
        {
          "id": 10749,
          "name": "мелодрама"
        }
      ],
      "homepage": "https://cinema.mosfilm.ru/films/35162/",
      "imdb_id": "tt0073179",
      "origin_country": [
        "SU"
      ],
      "production_companies": [
        {
          "id": 344,
          "logo_path": "/xenuUvcunUNpbaDOYGhWZERaym7.png",
          "name": "Mosfilm",
          "origin_country": "SU"
        }
      ],
      "production_countries": [
        {
          "iso_3166_1": "SU",
          "name": "Soviet Union"
        }
      ],
      "revenue": 0,
      "runtime": 184,
      "spoken_languages": [
        {
          "english_name": "Russian",
          "iso_639_1": "ru",
          "name": "Pусский"
        }
      ],
      "status": "Released",
      "tagline": "",
      "release_quality": "",
      "media_type": "movie",
      "categories": [
        "kinozal_movies_ru"
      ]
    },
    {
      "adult": false,
      "backdrop_path": null,
      "genre_ids": [
        18
      ],
      "id": 275253,
      "original_language": "ru",
      "original_title": "Көксерек",
      "overview": "Маленький сирота Курмаш живет с бабушкой и дядей - пастухом Ахангулом и, вопреки обычаям, берет в дом волчонка. Но постоянная травля окружающих приводит к тому, что мальчик отпускает Лютого на свободу, а сам покидает дядин дом. Проходит время. Мальчик, пожалев дядю, возвращается, а Лютый становится вожаком волчьей стаи. События в фильме происходят в начале XX века в казахской степи.",
      "popularity": 0.7233,
      "poster_path": "/vDxxtcvidbAUOo68HnmIZYAZUuk.jpg",
      "release_date": "1973-12-01",
      "title": "Лютый",
      "video": false,
      "vote_average": 4.6,
      "vote_count": 8,
      "belongs_to_collection": null,
      "budget": 0,
      "genres": [
        {
          "id": 18,
          "name": "драма"
        }
      ],
      "homepage": "",
      "imdb_id": "tt0144290",
      "origin_country": [
        "SU"
      ],
      "production_companies": [
        {
          "id": 40456,
          "logo_path": "/7aU4xI1sq3ZGXbNsX6uP0Z6VYlU.png",
          "name": "Kirghizfilm",
          "origin_country": "SU"
        },
        {
          "id": 232195,
          "logo_path": "/buy12sVmKaY1jiixLNCDZpc2MSo.png",
          "name": "Kazakhfilm",
          "origin_country": "SU"
        }
      ],
      "production_countries": [
        {
          "iso_3166_1": "SU",
          "name": "Soviet Union"
        }
      ],
      "revenue": 0,
      "runtime": 92,
      "spoken_languages": [
        {
          "english_name": "Russian",
          "iso_639_1": "ru",
          "name": "Pусский"
        }
      ],
      "status": "Released",
      "tagline": "",
      "release_quality": "2160p",
      "media_type": "movie",
      "categories": [
        "kinozal_movies_ru"
      ]
    }
  ]
}