{
  "category": {
    "id": "kinozal_tv",
    "title": "Сериалы"
  },
  "page": 5,
  "limit": 20,
  "total": 114,
  "items": [
    {
      "adult": false,
      "backdrop_path": "/tlAZ3g7EzHqWj0Yn6SXVAdFfAcE.jpg",
      "genre_ids": [
        18
      ],
      "id": 251600,
      "origin_country": [
        "CN"
      ],
      "original_language": "zh",
      "original_name": "千香",
      "overview": "Падение метеорита принесло в мир Древо Жизни, чей плод сулит власть над всем сущим. Три расы — бессмертные, демоны и люди — столетие вели кровавую войну за него. Лэй Сю Юань, мечтая спасти старшего брата, сближается с сиротой Сяо Бан Чуй, надеясь использовать её. Судьба сводит их в академии Чуфэн, где дружба перерастает в глубокую привязанность. Но тени прошлого открывают тайны их происхождения. Годы спустя Сяо Бан Чуй, ныне Цзян Ли Фэй, расцветает, привлекая тех, кто жаждет её магического дара. Лэй Сю Юань следует за ней в опасное путешествие, чтобы противостоять судьбе и вернуть мир в царства. Сможет ли он защитить возлюбленную от тьмы, грозящей поглотить их обоих? Экранизация романа Ши Сы Лан «Многообразие красоты».",
      "popularity": 48.1116,
      "poster_path": "/Cdnzjeu1pZ1ljF3ZtGV0a33Qq3.jpg",
      "first_air_date": "2026-06-27",
      "softcore": false,
      "name": "Тысяча ароматов",
      "vote_average": 9,
      "vote_count": 2,
      "created_by": [
        {
          "id": 4877063,
          "credit_id": "66ce7f7bd77109d51e721d5b",
          "name": "十四郎",
          "original_name": "十四郎",
          "gender": 1,
          "profile_path": null
        }
      ],
      "episode_run_time": [],
      "genres": [
        {
          "id": 18,
          "name": "драма"
        }
      ],
      "homepage": "https://v.youku.com/v_show/id_XNjQ4NzIwOTg1Ng==.html",
      "in_production": true,
      "languages": [
        "zh"
      ],
      "last_air_date": "2026-07-02",
      "last_episode_to_air": {
        "id": 6788033,
        "name": "Эпизод 13",
        "overview": "",
        "vote_average": 0,
        "vote_count": 0,
        "air_date": "2026-07-02",
        "episode_number": 13,
        "episode_type": "standard",
        "production_code": "",
        "runtime": 46,
        "season_number": 1,
        "show_id": 251600,
        "still_path": "/qHVltSH1fVpLkZPhfFoTex6xdZP.jpg"
      },
      "next_episode_to_air": {
        "id": 6788034,
        "name": "Эпизод 14",
        "overview": "",
        "vote_average": 0,
        "vote_count": 0,
        "air_date": "2026-07-03",
        "episode_number": 14,
        "episode_type": "standard",
        "production_code": "",
        "runtime": 46,
        "season_number": 1,
        "show_id": 251600,
        "still_path": "/9B0lY0SB9zNhoHWsihUGzlUNuUv.jpg"
      },
      "networks": [
        {
          "id": 1419,
          "logo_path": "/w2TeR3fvPZ9a617tNIF1oOfyPtk.png",
          "name": "Youku",
          "origin_country": "CN"
        }
      ],
      "number_of_episodes": 33,
      "number_of_seasons": 1,
      "production_companies": [
        {
          "id": 189547,
          "logo_path": null,
          "name": "H&R Century Pictures",
          "origin_country": "CN"
        },
        {
          "id": 48460,
          "logo_path": "/7m3BMwdstKRqw7qg5vSYW2S0HrR.png",
          "name": "Youku",
          "origin_country": "CN"
        }
      ],
      "production_countries": [
        {
          "iso_3166_1": "CN",
          "name": "China"
        }
      ],
      "seasons": [
        {
          "air_date": "2026-06-27",
          "episode_count": 33,
          "id": 388000,
          "name": "Сезон 1",
          "overview": "",
          "poster_path": "/ol5eEWh699n1Fhjfwr64icpurSB.jpg",
          "season_number": 1,
          "vote_average": 0
        }
      ],
      "spoken_languages": [
        {
          "english_name": "Mandarin",
          "iso_639_1": "zh",
          "name": "普通话"
        }
      ],
      "status": "Returning Series",
      "tagline": "",
      "type": "Scripted",
      "release_quality": "2160p",
      "media_type": "tv",
      "categories": [
        "kinozal_tv"
      ]
    },
    {
      "adult": false,
      "backdrop_path": "/sydzCACYJxeXuMbcw4OC8bNQkMx.jpg",
      "genre_ids": [
        18,
        10768
      ],
      "id": 250996,
      "origin_country": [
        "FR"
      ],
      "original_language": "fr",
      "original_name": "Kaboul",
      "overview": "Талибы находятся у ворот города, и Франция готовится эвакуировать свое посольство. Но падение Кабула разрушает все планы. Несколько дипломатов и полиция должны придумать план по спасению людей",
      "popularity": 5.0882,
      "poster_path": "/eNe7rihNslR3WkoK0S2r9HFjIcx.jpg",
      "first_air_date": "2025-03-31",
      "softcore": false,
      "name": "Кабул",
      "vote_average": 7.3,
      "vote_count": 22,
      "created_by": [
        {
          "id": 1863682,
          "credit_id": "660da9dbd400f3014a058d86",
          "name": "Thomas Finkielkraut",
          "original_name": "Thomas Finkielkraut",
          "gender": 2,
          "profile_path": null
        },
        {
          "id": 1957854,
          "credit_id": "660da9d4c8a5ac017c7b527f",
          "name": "Olivier Demangel",
          "original_name": "Olivier Demangel",
          "gender": 2,
          "profile_path": "/2wpsSvZU6q3ttRVYD6yp5eV6Ed1.jpg"
        }
      ],
      "episode_run_time": [
        52
      ],
      "genres": [
        {
          "id": 18,
          "name": "драма"
        },
        {
          "id": 10768,
          "name": "Война и Политика"
        }
      ],
      "homepage": "https://www.france.tv/france-2/kaboul/",
      "in_production": false,
      "languages": [
        "en",
        "el",
        "fr"
      ],
      "last_air_date": "2025-04-07",
      "last_episode_to_air": {
        "id": 5258180,
        "name": "Эпизод 6",
        "overview": "",
        "vote_average": 6,
        "vote_count": 1,
        "air_date": "2025-04-07",
        "episode_number": 6,
        "episode_type": "finale",
        "production_code": "",
        "runtime": 56,
        "season_number": 1,
        "show_id": 250996,
        "still_path": "/j9dCdQGj3lsJarMzwxC7UYJjVdl.jpg"
      },
      "next_episode_to_air": null,
      "networks": [
        {
          "id": 361,
          "logo_path": "/b1cFa5FcHHnpejKiPybXSPcqKjT.png",
          "name": "France 2",
          "origin_country": "FR"
        }
      ],
      "number_of_episodes": 6,
      "number_of_seasons": 1,
      "production_companies": [
        {
          "id": 11331,
          "logo_path": "/wcHhcw58wms26ejFLx1unYDT37n.png",
          "name": "Cinétévé",
          "origin_country": "FR"
        },
        {
          "id": 49068,
          "logo_path": null,
          "name": "24 25 Films",
          "origin_country": "FR"
        },
        {
          "id": 12407,
          "logo_path": "/g11ZDtSicimXi5MmwUznAsEomXZ.png",
          "name": "Panache Productions",
          "origin_country": "BE"
        },
        {
          "id": 12406,
          "logo_path": "/e89tcj2PpfFffwA0etxuGftj0YU.png",
          "name": "La Compagnie Cinématographique",
          "origin_country": "BE"
        },
        {
          "id": 51401,
          "logo_path": "/fVS0ghIwUgjwpHj2vJonkAOlyI5.png",
          "name": "Blonde Audiovisual Productions",
          "origin_country": "GR"
        },
        {
          "id": 4606,
          "logo_path": "/otZHbf1HmzLRQsZFSqJXkf8EHz7.png",
          "name": "ZDF",
          "origin_country": "DE"
        },
        {
          "id": 115308,
          "logo_path": "/5FP51Vqper685TpfOurr9plMRwb.png",
          "name": "Cosmote TV",
          "origin_country": "GR"
        },
        {
          "id": 7131,
          "logo_path": "/qpFsGoa96SytbWkhtkkpllu5Cch.png",
          "name": "France Télévisions",
          "origin_country": "FR"
        },
        {
          "id": 154744,
          "logo_path": "/qYIEHRctL3YFth36F1LwhEQvOl5.png",
          "name": "Rai Fiction",
          "origin_country": "IT"
        },
        {
          "id": 100462,
          "logo_path": "/24dhPKt8sDtfWfNs1rsVtskOwZZ.png",
          "name": "BNNVARA",
          "origin_country": "NL"
        },
        {
          "id": 12025,
          "logo_path": "/sLVmKLJ2E0KSsfKiIYDjo4v6Y5l.png",
          "name": "VRT",
          "origin_country": "BE"
        },
        {
          "id": 2999,
          "logo_path": "/zGSqFee9aDgDuLD6vcs2mcJUem4.png",
          "name": "SVT",
          "origin_country": "SE"
        },
        {
          "id": 119,
          "logo_path": "/1di2gITGUZr730AMuMKiCrP90Vl.png",
          "name": "DR",
          "origin_country": "DK"
        },
        {
          "id": 5975,
          "logo_path": "/vvjgoKygWWYZvYyidT3RmOCq5If.png",
          "name": "YLE",
          "origin_country": "FI"
        },
        {
          "id": 17496,
          "logo_path": "/o024AfoFk05dTk3Kz6BNTbkAwT.png",
          "name": "RÚV",
          "origin_country": "IS"
        },
        {
          "id": 109843,
          "logo_path": "/iwkwIEXWIPApzedElW5sY8LFZSx.png",
          "name": "NRK",
          "origin_country": "NO"
        }
      ],
      "production_countries": [
        {
          "iso_3166_1": "DK",
          "name": "Denmark"
        },
        {
          "iso_3166_1": "SE",
          "name": "Sweden"
        },
        {
          "iso_3166_1": "FI",
          "name": "Finland"
        },
        {
          "iso_3166_1": "FR",
          "name": "France"
        },
        {
          "iso_3166_1": "IS",
          "name": "Iceland"
        },
        {
          "iso_3166_1": "GR",
          "name": "Greece"
        },
        {
          "iso_3166_1": "NL",
          "name": "Netherlands"
        },
        {
          "iso_3166_1": "NO",
          "name": "Norway"
        },
        {
          "iso_3166_1": "IT",
          "name": "Italy"
        }
      ],
      "seasons": [
        {
          "air_date": "2025-03-31",
          "episode_count": 6,
          "id": 386912,
          "name": "Сезон 1",
          "overview": "",
          "poster_path": "/Awi9QBlnB0FCeLaPBGeXwTbiOMX.jpg",
          "season_number": 1,
          "vote_average": 6.5
        }
      ],
      "spoken_languages": [
        {
          "english_name": "English",
          "iso_639_1": "en",
          "name": "English"
        },
        {
          "english_name": "Greek",
          "iso_639_1": "el",
          "name": "ελληνικά"
        },
        {
          "english_name": "French",
          "iso_639_1": "fr",
          "name": "Français"
        }
      ],
      "status": "Ended",
      "tagline": "",
      "type": "Miniseries",
      "release_quality": "1080p",
      "media_type": "tv",
      "categories": [
        "kinozal_tv"
      ]
    },
    {
      "adult": false,
      "backdrop_path": "/x0zAZmhH4Pbo6PctR5WzWoJ7SAV.jpg",
      "genre_ids": [
        18
      ],
      "id": 316830,
      "origin_country": [
        "US"
      ],
      "original_language": "en",
      "original_name": "Seeking Persephone",
      "overview": "Начало XIX века. Персефона Ланкастер выходит замуж за Адама Бойса, герцога-затворника, чтобы помочь своей семье. Девушка пытается установить связь с одиноким человеком, который скрывается за очерствевшим характером и внушительными владениями. Постепенно Персефона растапливает холодный нрав Адама, и между ними возникает привязанность. Сериал снят по одноимённому роману Сары М. Иден — это первая книга из серии «Ланкастеры».",
      "popularity": 32.3633,
      "poster_path": "/tJsS5oFvcKsJ3NdlTbuG7nyCDIK.jpg",
      "first_air_date": "2026-03-01",
      "softcore": false,
      "name": "В поисках Персефоны",
      "vote_average": 8.8,
      "vote_count": 11,
      "created_by": [
        {
          "id": 5357682,
          "credit_id": "69cb5f1e48df6c4a35c353e8",
          "name": "Sarah M. Eden",
          "original_name": "Sarah M. Eden",
          "gender": 0,
          "profile_path": null
        }
      ],
      "episode_run_time": [],
      "genres": [
        {
          "id": 18,
          "name": "драма"
        }
      ],
      "homepage": "https://www.seekingpersephonemovie.com",
      "in_production": false,
      "languages": [
        "en"
      ],
      "last_air_date": "2026-03-01",
      "last_episode_to_air": {
        "id": 7050669,
        "name": "Эпизод 4",
        "overview": "",
        "vote_average": 9,
        "vote_count": 1,
        "air_date": "2026-03-01",
        "episode_number": 4,
        "episode_type": "finale",
        "production_code": "",
        "runtime": 43,
        "season_number": 1,
        "show_id": 316830,
        "still_path": "/9ifdx658Ew6AEVHsjcHhpCEgGw5.jpg"
      },
      "next_episode_to_air": null,
      "networks": [
        {
          "id": 1024,
          "logo_path": "/w7HfLNm9CWwRmAMU58udl2L7We7.png",
          "name": "Prime Video",
          "origin_country": ""
        },
        {
          "id": 9117,
          "logo_path": "/tPfiQCrrpA1KfGE5Zc6zL92osdZ.png",
          "name": "Fandango at Home",
          "origin_country": "US"
        }
      ],
      "number_of_episodes": 4,
      "number_of_seasons": 1,
      "production_companies": [
        {
          "id": 9074,
          "logo_path": null,
          "name": "Mainstay Productions",
          "origin_country": "US"
        }
      ],
      "production_countries": [
        {
          "iso_3166_1": "US",
          "name": "United States of America"
        }
      ],
      "seasons": [
        {
          "air_date": "2026-03-01",
          "episode_count": 4,
          "id": 505663,
          "name": "Сезон 1",
          "overview": "",
          "poster_path": "/tJsS5oFvcKsJ3NdlTbuG7nyCDIK.jpg",
          "season_number": 1,
          "vote_average": 0
        }
      ],
      "spoken_languages": [
        {
          "english_name": "English",
          "iso_639_1": "en",
          "name": "English"
        }
      ],
      "status": "Ended",
      "tagline": "",
      "type": "Miniseries",
      "release_quality": "1080p",
      "media_type": "tv",
      "categories": [
        "kinozal_tv"
      ]
    },
    {
      "adult": false,
      "backdrop_path": "/uHLNi3Fz3p8Ocf36AGKbw8xcH2m.jpg",
      "genre_ids": [
        18
      ],
      "id": 315610,
      "origin_country": [
        "PL"
      ],
      "original_language": "pl",
      "original_name": "Proud",
      "overview": "История Филиппа, молодого и безответственного гея, который живет в убеждении, что мир принадлежит ему, и это никогда не изменится. Он наглый, безнаказанный, беззаботный, нетерпеливый, красивый и молодой. Внутренняя неуверенность в себе компенсируется высокомерием, восторгом в глазах окружающих и работой модели. Когда происходит семейная трагедия, весь его мир переворачивается с ног на голову.",
      "popularity": 14.8872,
      "poster_path": "/aJEarJ7ASffiTYeHt7RtOAXy7vr.jpg",
      "first_air_date": "2026-06-12",
      "softcore": false,
      "name": "Гордый",
      "vote_average": 4.4,
      "vote_count": 19,
      "created_by": [],
      "episode_run_time": [],
      "genres": [
        {
          "id": 18,
          "name": "драма"
        }
      ],
      "homepage": "https://www.hbomax.com/shows/proud/920dc342-cb8a-4c38-a0a5-04ee899dd238",
      "in_production": true,
      "languages": [
        "pl"
      ],
      "last_air_date": "2026-06-26",
      "last_episode_to_air": {
        "id": 7294350,
        "name": "Эпизод 3",
        "overview": "",
        "vote_average": 1,
        "vote_count": 2,
        "air_date": "2026-06-26",
        "episode_number": 3,
        "episode_type": "standard",
        "production_code": "",
        "runtime": 39,
        "season_number": 1,
        "show_id": 315610,
        "still_path": "/8vtbPo3aX8DCOLH54TWSm5STv3V.jpg"
      },
      "next_episode_to_air": {
        "id": 7294352,
        "name": "Эпизод 4",
        "overview": "",
        "vote_average": 0,
        "vote_count": 0,
        "air_date": "2026-07-03",
        "episode_number": 4,
        "episode_type": "standard",
        "production_code": "",
        "runtime": null,
        "season_number": 1,
        "show_id": 315610,
        "still_path": null
      },
      "networks": [
        {
          "id": 8304,
          "logo_path": "/gqWI9y0owo9sxgzZD7TXOeILYI9.png",
          "name": "HBO Max",
          "origin_country": ""
        }
      ],
      "number_of_episodes": 8,
      "number_of_seasons": 1,
      "production_companies": [
        {
          "id": 234272,
          "logo_path": null,
          "name": "Magnolia Films",
          "origin_country": "PL"
        }
      ],
      "production_countries": [
        {
          "iso_3166_1": "PL",
          "name": "Poland"
        }
      ],
      "seasons": [
        {
          "air_date": "2026-06-12",
          "episode_count": 8,
          "id": 503458,
          "name": "Сезон 1",
          "overview": "",
          "poster_path": "/v7xmSCuGqVwSHfXkjAgZEEtl1Gr.jpg",
          "season_number": 1,
          "vote_average": 2.1
        }
      ],
      "spoken_languages": [
        {
          "english_name": "Polish",
          "iso_639_1": "pl",
          "name": "Polski"
        }
      ],
      "status": "Returning Series",
      "tagline": "",
      "type": "Scripted",
      "release_quality": "1080p",
      "media_type": "tv",
      "categories": [
        "kinozal_tv"
      ]
    },
    {
      "adult": false,
      "backdrop_path": "/gfBw8ZoGtRHSmSD5jo0McgwDzYd.jpg",
      "genre_ids": [
        10759,
        35,
        18
      ],
      "id": 297712,
      "origin_country": [
        "KR"
      ],
      "original_language": "ko",
      "original_name": "오십프로",
      "overview": "Судьба сводит героев на отдалённом острове Ёнсон. Из-за очередного происшествия им приходится вновь объединить усилия: прошлое напоминает о себе, и каждому нужно выяснить правду, попутно учась доверять напарнику. В сериале удачно смешались динамичные экшен-сцены (драки, погони), тонкий юмор (контраст между возрастом героев и их активностью) и глубокая драма - у каждого свой груз прошлого и поиск искупления.",
      "popularity": 13.3673,
      "poster_path": "/eu8AhC5qzPgbKclpPWMF6qkCDL8.jpg",
      "first_air_date": "2026-05-22",
      "softcore": false,
      "name": "50-летние профи",
      "vote_average": 5.9,
      "vote_count": 7,
      "created_by": [
        {
          "id": 6153118,
          "credit_id": "69e4dd8e44d13d99ae1978fe",
          "name": "장원섭",
          "original_name": "장원섭",
          "gender": 0,
          "profile_path": null
        }
      ],
      "episode_run_time": [],
      "genres": [
        {
          "id": 10759,
          "name": "Боевик и Приключения"
        },
        {
          "id": 35,
          "name": "комедия"
        },
        {
          "id": 18,
          "name": "драма"
        }
      ],
      "homepage": "https://program.imbc.com/FiftiesProfessionals",
      "in_production": false,
      "languages": [
        "ko"
      ],
      "last_air_date": "2026-06-27",
      "last_episode_to_air": {
        "id": 7271639,
        "name": "Эпизод 12",
        "overview": "",
        "vote_average": 0,
        "vote_count": 0,
        "air_date": "2026-06-27",
        "episode_number": 12,
        "episode_type": "finale",
        "production_code": "",
        "runtime": 64,
        "season_number": 1,
        "show_id": 297712,
        "still_path": "/6d7Q0lTtG4LgTjih9Aytg4qTzYJ.jpg"
      },
      "next_episode_to_air": null,
      "networks": [
        {
          "id": 97,
          "logo_path": "/pOSCKaZhndUFYtxHXjQOV6xJi1s.png",
          "name": "MBC",
          "origin_country": "KR"
        }
      ],
      "number_of_episodes": 12,
      "number_of_seasons": 1,
      "production_companies": [
        {
          "id": 202352,
          "logo_path": "/hun8TjlJ1F9DKNmh6yNpoucdHtx.png",
          "name": "Jumbo Film",
          "origin_country": "KR"
        },
        {
          "id": 86418,
          "logo_path": "/vzzqRwqTin3iAAMw2JlrmVPNnPa.png",
          "name": "Studio Dragon",
          "origin_country": "KR"
        }
      ],
      "production_countries": [
        {
          "iso_3166_1": "KR",
          "name": "South Korea"
        }
      ],
      "seasons": [
        {
          "air_date": "2026-05-22",
          "episode_count": 12,
          "id": 468597,
          "name": "Сезон 1",
          "overview": "",
          "poster_path": "/hfVprGXtfxgCiBCZBktgXyJgefG.jpg",
          "season_number": 1,
          "vote_average": 0
        }
      ],
      "spoken_languages": [
        {
          "english_name": "Korean",
          "iso_639_1": "ko",
          "name": "한국어/조선말"
        }
      ],
      "status": "Ended",
      "tagline": "",
      "type": "Miniseries",
      "release_quality": "1080p",
      "media_type": "tv",
      "categories": [
        "kinozal_tv"
      ]
    },
    {
      "adult": false,
      "backdrop_path": "/emEJdHqgr0dLTpchPmifiGM2DR.jpg",
      "genre_ids": [
        35
      ],
      "id": 65150,
      "origin_country": [
        "US"
      ],
      "original_language": "en",
      "original_name": "Vice Principals",
      "overview": "Чёрная комедия про двух истеричных завучей  средней школы, которые по иронии судьбы отвечают за дисциплину и учебный  план. После того, как директор уходит на пенсию, завучи затевают  эпическую борьбу за должность.",
      "popularity": 13.9622,
      "poster_path": "/skUwMCeFqTnNAzFRrThPXjdUHtQ.jpg",
      "first_air_date": "2016-07-17",
      "softcore": false,
      "name": "Завучи",
      "vote_average": 7.206,
      "vote_count": 279,
      "created_by": [
        {
          "id": 62862,
          "credit_id": "568a90afc3a36860e902b57c",
          "name": "Дэнни МакБрайд",
          "original_name": "Danny McBride",
          "gender": 2,
          "profile_path": "/sVFPzl2t5QlGudQKWAszIWZCXZv.jpg"
        },
        {
          "id": 54710,
          "credit_id": "5a209cb20e0a264ccd09b1b2",
          "name": "Джоди Хилл",
          "original_name": "Jody Hill",
          "gender": 2,
          "profile_path": "/ch0paHlLOeUz1jfhzyOtohyjEpg.jpg"
        }
      ],
      "episode_run_time": [],
      "genres": [
        {
          "id": 35,
          "name": "комедия"
        }
      ],
      "homepage": "http://www.hbo.com/vice-principals",
      "in_production": false,
      "languages": [
        "en"
      ],
      "last_air_date": "2017-11-12",
      "last_episode_to_air": {
        "id": 1368909,
        "name": "Эпизод 9",
        "overview": "",
        "vote_average": 7.4,
        "vote_count": 5,
        "air_date": "2017-11-12",
        "episode_number": 9,
        "episode_type": "finale",
        "production_code": "",
        "runtime": 31,
        "season_number": 2,
        "show_id": 65150,
        "still_path": "/f77U0BNCl5dY8oEi2Bs11dq4r03.jpg"
      },
      "next_episode_to_air": null,
      "networks": [
        {
          "id": 49,
          "logo_path": "/tuomPhY2UtuPTqqFnKMVHvSb724.png",
          "name": "HBO",
          "origin_country": "US"
        }
      ],
      "number_of_episodes": 18,
      "number_of_seasons": 2,
      "production_companies": [
        {
          "id": 20848,
          "logo_path": "/xfQxrdf3WumiLoaMS2F3xWO6nKF.png",
          "name": "Rough House Pictures",
          "origin_country": "US"
        },
        {
          "id": 3268,
          "logo_path": "/tuomPhY2UtuPTqqFnKMVHvSb724.png",
          "name": "HBO",
          "origin_country": "US"
        }
      ],
      "production_countries": [
        {
          "iso_3166_1": "US",
          "name": "United States of America"
        }
      ],
      "seasons": [
        {
          "air_date": "2016-07-17",
          "episode_count": 9,
          "id": 73539,
          "name": "Сезон 1",
          "overview": "",
          "poster_path": "/4MKRkYj0bOqffWpn2Rdu0zZ3RcN.jpg",
          "season_number": 1,
          "vote_average": 6.9
        },
        {
          "air_date": "2017-09-17",
          "episode_count": 9,
          "id": 92127,
          "name": "Сезон 2",
          "overview": "",
          "poster_path": "/rraxyaaX33sxgrDG3r7bBV2thj8.jpg",
          "season_number": 2,
          "vote_average": 7.2
        }
      ],
      "spoken_languages": [
        {
          "english_name": "English",
          "iso_639_1": "en",
          "name": "English"
        }
      ],
      "status": "Ended",
      "tagline": "",
      "type": "Scripted",
      "release_quality": "1080p",
      "media_type": "tv",
      "categories": [
        "kinozal_tv"
      ]
    },
    {
      "adult": false,
      "backdrop_path": "/bq28ajZaoMyzEIm6REelqyqtEDZ.jpg",
      "genre_ids": [
        10765,
        10759
      ],
      "id": 76479,
      "origin_country": [
        "US"
      ],
      "original_language": "en",
      "original_name": "The Boys",
      "overview": "События разворачивается в 2000-е в мире, где существуют супергерои. Именно они являются настоящими звёздами, которых все знают и обожают. Но за идеальным фасадом скрывается гораздо более мрачный мир наркотиков и секса, а большинство героев в жизни не самые приятные люди. Для контроля за супергероями ЦРУ создаёт специальный отряд, неофициально известный как «Пацаны», суровые члены которого всегда готовы поставить зазнавшегося героя на место самым жестоким способом.",
      "popularity": 185.0451,
      "poster_path": "/3NqlBDpWI83TgQ9nmeFwTVxEmtZ.jpg",
      "first_air_date": "2019-07-25",
      "name": "Пацаны",
      "vote_average": 8.4,
      "vote_count": 11751,
      "created_by": [
        {
          "id": 58321,
          "credit_id": "5f3814c011c066003637f6a8",
          "name": "Эрик Крипке",
          "original_name": "Eric Kripke",
          "gender": 2,
          "profile_path": "/dd7EgfOEKPqQxWtBfAvjYZahbSc.jpg"
        }
      ],
      "episode_run_time": [],
      "genres": [
        {
          "id": 10765,
          "name": "НФ и Фэнтези"
        },
        {
          "id": 10759,
          "name": "Боевик и Приключения"
        }
      ],
      "homepage": "https://www.amazon.com/dp/B07QQQHK1Y",
      "in_production": true,
      "languages": [
        "en"
      ],
      "last_air_date": "2024-07-18",
      "last_episode_to_air": {
        "id": 4217016,
        "name": "Финал четвертого сезона",
        "overview": "Призываем всех патриотов! Мы не позволим, чтобы завтра эти сфальсифицированные выборы были утверждены! Мы должны остановить воука Боба Сингера, у которого на повестке дня уничтожение суперов! ГОТОВЬТЕСЬ К ВОЙНЕ! #Мы_едины_с_Воут",
        "vote_average": 8.238,
        "vote_count": 80,
        "air_date": "2024-07-18",
        "episode_number": 8,
        "episode_type": "finale",
        "production_code": "THBY 408",
        "runtime": 69,
        "season_number": 4,
        "show_id": 76479,
        "still_path": "/kv7DTgyuKz5gsSwfoH92Tnam0lA.jpg"
      },
      "next_episode_to_air": {
        "id": 5788295,
        "name": "Эпизод 1",
        "overview": "",
        "vote_average": 10,
        "vote_count": 3,
        "air_date": "2026-04-08",
        "episode_number": 1,
        "episode_type": "standard",
        "production_code": "",
        "runtime": 64,
        "season_number": 5,
        "show_id": 76479,
        "still_path": "/8IjPgjPdwHjlXbxn8ixIGrFFFef.jpg"
      },
      "networks": [
        {
          "id": 1024,
          "logo_path": "/w7HfLNm9CWwRmAMU58udl2L7We7.png",
          "name": "Prime Video",
          "origin_country": ""
        }
      ],
      "number_of_episodes": 40,
      "number_of_seasons": 5,
      "production_companies": [
        {
          "id": 20580,
          "logo_path": "/oRR9EXVoKP9szDkVKlze5HVJS7g.png",
          "name": "Amazon Studios",
          "origin_country": "US"
        },
        {
          "id": 333,
          "logo_path": "/5xUJfzPZ8jWJUDzYtIeuPO4qPIa.png",
          "name": "Original Film",
          "origin_country": "US"
        },
        {
          "id": 11073,
          "logo_path": "/wHs44fktdoj6c378ZbSWfzKsM2Z.png",
          "name": "Sony Pictures Television",
          "origin_country": "US"
        },
        {
          "id": 38398,
          "logo_path": null,
          "name": "Kripke Enterprises",
          "origin_country": "US"
        },
        {
          "id": 16615,
          "logo_path": "/5au3v0r2brGaegO9EQ0nodLkmQ1.png",
          "name": "Point Grey Pictures",
          "origin_country": "US"
        },
        {
          "id": 2526,
          "logo_path": "/kzIW6QWhacDwzGoXEIWhac8rb70.png",
          "name": "Kickstart Entertainment",
          "origin_country": "US"
        },
        {
          "id": 33728,
          "logo_path": null,
          "name": "NightSky Productions",
          "origin_country": "US"
        },
        {
          "id": 210099,
          "logo_path": "/g5oRCNCi8kNVb8gEoSoIcqkhjmR.png",
          "name": "Amazon MGM Studios",
          "origin_country": "US"
        }
      ],
      "production_countries": [
        {
          "iso_3166_1": "US",
          "name": "United States of America"
        }
      ],
      "seasons": [
        {
          "air_date": "2020-09-10",
          "episode_count": 58,
          "id": 163277,
          "name": "Спецматериалы",
          "overview": "",
          "poster_path": "/cCXG81dSCPXcqYm6gTHlwtXocti.jpg",
          "season_number": 0,
          "vote_average": 0
        },
        {
          "air_date": "2019-07-25",
          "episode_count": 8,
          "id": 98085,
          "name": "Сезон 1",
          "overview": "В мире, где супергерои поддаются темной стороне их невероятной популярности и славы, главные герои сериала «ПАЦАНЫ» - это группа борцов за справедливость, которых неофициально называют Пацанами. Их миссия - сместить коррумпированных супергероев, будучи вооруженными лишь решимостью и готовностью биться не по правилам.",
          "poster_path": "/29gttiszw8JHiQ4qTEcXcym2F4f.jpg",
          "season_number": 1,
          "vote_average": 8.1
        },
        {
          "air_date": "2020-09-03",
          "episode_count": 8,
          "id": 154681,
          "name": "Сезон 2",
          "overview": "Сезон 2 полон напряжения и отчаяния. Бутчер, Хьюи и остальные пытаются оправиться от потерь первого сезона. Они скрываются от властей и борются с супергероями. «Воут», компания, управляющая супергероями, пользуется паникой по поводу угрозы суперзлодеев. Появляется новая героиня – Гроза. Она устраивает в компании встряску и бросает вызов Хоумлендеру, который и так нестабилен.",
          "poster_path": "/8WwLNUXlLVIFSIZKbzcJPxy2tqC.jpg",
          "season_number": 2,
          "vote_average": 8
        },
        {
          "air_date": "2022-06-02",
          "episode_count": 8,
          "id": 215686,
          "name": "Сезон 3",
          "overview": "Выдался спокойный год. Хоумлендер усмирен. Бутчер работает на правительство под надзором не кого иного как Хьюи. Но обоим невтерпёж превратить тихую мирную жизнь в кровавое месиво. И когда Парни узнают о таинственном оружии против суперов, они сталкиваются с Семеркой, развязывая войну и преследуя первого легендарного супергероя – Солдатика.",
          "poster_path": "/emg4x9eHzikUW8Q7FxvGSRrJpBH.jpg",
          "season_number": 3,
          "vote_average": 8
        },
        {
          "air_date": "2024-06-13",
          "episode_count": 8,
          "id": 305753,
          "name": "Сезон 4",
          "overview": "Мир на грани катастрофы. Виктория Ньюман близко подобралась к Овальному кабинету. Она находится под жестким контролем Хоумлендера, укрепляющего свои позиции. Бутчеру осталось жить месяцы, он потерял сына Бекки и место лидера Парней. Остальным членам команды надоела его ложь. Ставки как никогда высоки, и они должны найти способ действовать заодно и спасти мир, пока не стало слишком поздно.",
          "poster_path": "/cDjn2BxMVswXFW0k58sKcEWcakt.jpg",
          "season_number": 4,
          "vote_average": 7.5
        },
        {
          "air_date": "2026-04-08",
          "episode_count": 8,
          "id": 393831,
          "name": "Сезон 5",
          "overview": "Хоумлендер контролирует Америку посредством фашистского террора и заключает диссидентов в Лагеря свободы. Бутчер, Хьюи, Энни и остальные Парни ведут отчаянное сопротивление при ничтожных шансах остановить тираническое правление Хоумлендера.",
          "poster_path": "/AkKMNECWenIA1d57U9VDUuAG701.jpg",
          "season_number": 5,
          "vote_average": 9.5
        }
      ],
      "spoken_languages": [
        {
          "english_name": "English",
          "iso_639_1": "en",
          "name": "English"
        }
      ],
      "status": "Returning Series",
      "tagline": "«Не стоит встречаться со своими героями»",
      "type": "Scripted",
      "release_quality": "1080p",
      "media_type": "tv",
      "categories": [
        "kinozal_tv"
      ]
    },
    {
      "adult": false,
      "backdrop_path": "/ceglapC9MOGAtksG1oOZhDiN1SR.jpg",
      "genre_ids": [
        10766
      ],
      "id": 133031,
      "origin_country": [
        "CO"
      ],
      "original_language": "es",
      "original_name": "La Traición",
      "overview": "Близнецы Уго и Алсидес де Медина внешне почти неотличимы. Даже привязанности у них одинаковы, они любят одну женщину – прелестную Соледад. В конце чопорного XIX века это казалось верхом неприличия. К тому же один из братьев, Уго, слывет удачливым и далеким от морали сердцеедом. История начинается с дуэли, на которую вызвал Уго оскорбленный брат девушки, за которой ухаживал любвеобильный кабальеро.",
      "popularity": 8.7144,
      "poster_path": "/b89IDvczzt9htnk3JQNSrxOsXnw.jpg",
      "first_air_date": "2008-06-27",
      "softcore": false,
      "name": "Предательство",
      "vote_average": 8.5,
      "vote_count": 4,
      "created_by": [
        {
          "id": 5258971,
          "credit_id": "67b7215fe484fc21541a0e78",
          "name": "Jose Fernando Perez",
          "original_name": "Jose Fernando Perez",
          "gender": 0,
          "profile_path": null
        }
      ],
      "episode_run_time": [
        45
      ],
      "genres": [
        {
          "id": 10766,
          "name": "Мыльная опера"
        }
      ],
      "homepage": "",
      "in_production": false,
      "languages": [],
      "last_air_date": "2008-06-27",
      "last_episode_to_air": {
        "id": 3199232,
        "name": "Эпизод 1",
        "overview": "",
        "vote_average": 0,
        "vote_count": 0,
        "air_date": "2008-06-27",
        "episode_number": 1,
        "episode_type": "standard",
        "production_code": "",
        "runtime": 45,
        "season_number": 1,
        "show_id": 133031,
        "still_path": null
      },
      "next_episode_to_air": null,
      "networks": [],
      "number_of_episodes": 107,
      "number_of_seasons": 1,
      "production_companies": [
        {
          "id": 132023,
          "logo_path": null,
          "name": "RTI Television",
          "origin_country": "CO"
        }
      ],
      "production_countries": [
        {
          "iso_3166_1": "CO",
          "name": "Colombia"
        }
      ],
      "seasons": [
        {
          "air_date": "2008-06-27",
          "episode_count": 107,
          "id": 209847,
          "name": "Сезон 1",
          "overview": "",
          "poster_path": null,
          "season_number": 1,
          "vote_average": 0
        }
      ],
      "spoken_languages": [],
      "status": "Ended",
      "tagline": "",
      "type": "Scripted",
      "release_quality": "",
      "media_type": "tv",
      "categories": [
        "kinozal_tv"
      ]
    },
    {
      "adult": false,
      "backdrop_path": "/zQUMl21oCbFQ9FxodA5JbOndMXQ.jpg",
      "genre_ids": [
        10759,
        18,
        80,
        9648
      ],
      "id": 247704,
      "origin_country": [
        "GB"
      ],
      "original_language": "en",
      "original_name": "Red Eye",
      "overview": "Офицер лондонской полиции Хана Ли сопровождает доктора Мэттью Нолана в Пекин, где его обвиняют в преступлении. На борту рейса 357 она сталкивается с развивающимся заговором, в котором количество убийств неуклонно увеличивается.",
      "popularity": 12.7114,
      "poster_path": "/myYfWeBDTGZlFChauaYDHpWIDEb.jpg",
      "first_air_date": "2024-04-21",
      "softcore": false,
      "name": "Ночной рейс",
      "vote_average": 7.1,
      "vote_count": 117,
      "created_by": [
        {
          "id": 57271,
          "credit_id": "65df38fa7614210185d6101b",
          "name": "Peter A. Dowling",
          "original_name": "Peter A. Dowling",
          "gender": 2,
          "profile_path": null
        }
      ],
      "episode_run_time": [],
      "genres": [
        {
          "id": 10759,
          "name": "Боевик и Приключения"
        },
        {
          "id": 18,
          "name": "драма"
        },
        {
          "id": 80,
          "name": "криминал"
        },
        {
          "id": 9648,
          "name": "детектив"
        }
      ],
      "homepage": "https://www.itv.com/watch/red-eye/10a4437",
      "in_production": true,
      "languages": [
        "en"
      ],
      "last_air_date": "2026-01-12",
      "last_episode_to_air": {
        "id": 6782401,
        "name": "Эпизод 6",
        "overview": "",
        "vote_average": 8,
        "vote_count": 5,
        "air_date": "2026-01-12",
        "episode_number": 6,
        "episode_type": "finale",
        "production_code": "",
        "runtime": 48,
        "season_number": 2,
        "show_id": 247704,
        "still_path": "/qGAdoZ720CupEklEQfNGQmdzG6b.jpg"
      },
      "next_episode_to_air": null,
      "networks": [
        {
          "id": 9,
          "logo_path": "/oz9pjTHnBUmlju8OkaTymhKbh6C.png",
          "name": "ITV1",
          "origin_country": "GB"
        }
      ],
      "number_of_episodes": 12,
      "number_of_seasons": 2,
      "production_companies": [
        {
          "id": 82996,
          "logo_path": "/sxxPhM3Qt3OCQaFUyeegZ8eqcs9.png",
          "name": "Bad Wolf",
          "origin_country": "GB"
        },
        {
          "id": 3448,
          "logo_path": "/dcA8JDfnnQPMaq8lv2CCiYrNe0S.png",
          "name": "ITV",
          "origin_country": "GB"
        }
      ],
      "production_countries": [
        {
          "iso_3166_1": "GB",
          "name": "United Kingdom"
        }
      ],
      "seasons": [
        {
          "air_date": "2024-04-21",
          "episode_count": 6,
          "id": 381429,
          "name": "Сезон 1",
          "overview": "",
          "poster_path": "/5NaxLAJXJT2eC2m0o06cycJlSl7.jpg",
          "season_number": 1,
          "vote_average": 7
        },
        {
          "air_date": "2026-01-01",
          "episode_count": 6,
          "id": 490866,
          "name": "Сезон 2",
          "overview": "",
          "poster_path": "/z7IzsY0qIfSMZy22IsWuWuGZVHT.jpg",
          "season_number": 2,
          "vote_average": 6.8
        }
      ],
      "spoken_languages": [
        {
          "english_name": "English",
          "iso_639_1": "en",
          "name": "English"
        }
      ],
      "status": "Returning Series",
      "tagline": "",
      "type": "Scripted",
      "release_quality": "",
      "media_type": "tv",
      "categories": [
        "kinozal_tv"
      ]
    },
    {
      "adult": false,
      "backdrop_path": "/iTt37Rl8AidvU5aQf5M4odroCuF.jpg",
      "genre_ids": [
        18
      ],
      "id": 255055,
      "origin_country": [
        "US"
      ],
      "original_language": "en",
      "original_name": "Doc",
      "overview": "Доктор Эми Ларсен теряет память после автомобильной аварии. Она не помнит последние 8 лет своей жизни: ни пациентов, ни коллег, ни развода с мужем, ни взросления дочери. Эми возвращается к медицинской практике, но вынуждена опять стать интерном, чтобы построить свою жизнь заново.",
      "popularity": 15.4833,
      "poster_path": "/kOATr8E3OzOdrqoViMEUMQH75Nz.jpg",
      "first_air_date": "2025-01-07",
      "softcore": false,
      "name": "Док",
      "vote_average": 7.118,
      "vote_count": 68,
      "created_by": [
        {
          "id": 1227503,
          "credit_id": "67978f9e760f51e17d2b3e96",
          "name": "Barbie Kligman",
          "original_name": "Barbie Kligman",
          "gender": 1,
          "profile_path": null
        }
      ],
      "episode_run_time": [],
      "genres": [
        {
          "id": 18,
          "name": "драма"
        }
      ],
      "homepage": "https://www.fox.com/detail/series/SER003214BDSJ/doc",
      "in_production": true,
      "languages": [
        "en",
        "ja",
        "hu"
      ],
      "last_air_date": "2026-04-14",
      "last_episode_to_air": {
        "id": 7041663,
        "name": "Эпизод 22",
        "overview": "",
        "vote_average": 7.1,
        "vote_count": 5,
        "air_date": "2026-04-14",
        "episode_number": 22,
        "episode_type": "finale",
        "production_code": "",
        "runtime": 44,
        "season_number": 2,
        "show_id": 255055,
        "still_path": "/yE6wOv1NL05HlJ4MpeOOjRp5jC0.jpg"
      },
      "next_episode_to_air": null,
      "networks": [
        {
          "id": 19,
          "logo_path": "/1DSpHrWyOORkL9N2QHX7Adt31mQ.png",
          "name": "FOX",
          "origin_country": "US"
        }
      ],
      "number_of_episodes": 32,
      "number_of_seasons": 2,
      "production_companies": [
        {
          "id": 11073,
          "logo_path": "/wHs44fktdoj6c378ZbSWfzKsM2Z.png",
          "name": "Sony Pictures Television",
          "origin_country": "US"
        },
        {
          "id": 187918,
          "logo_path": "/1spIsLYLVuY6RxM3rIzjjFAa9re.png",
          "name": "FOX Entertainment Studios",
          "origin_country": "US"
        },
        {
          "id": 56214,
          "logo_path": null,
          "name": "Channel Road Productions",
          "origin_country": "US"
        },
        {
          "id": 787,
          "logo_path": "/cCefBs1t7jxtiz3eCxBp9yxrxGx.png",
          "name": "3 Arts Entertainment",
          "origin_country": "US"
        },
        {
          "id": 271953,
          "logo_path": null,
          "name": "Avenue K Productions",
          "origin_country": "US"
        }
      ],
      "production_countries": [
        {
          "iso_3166_1": "US",
          "name": "United States of America"
        }
      ],
      "seasons": [
        {
          "air_date": "2025-01-07",
          "episode_count": 10,
          "id": 394972,
          "name": "Сезон 1",
          "overview": "",
          "poster_path": "/zk8YaULyHzzDx5WwrEV3q1QCtcn.jpg",
          "season_number": 1,
          "vote_average": 7.9
        },
        {
          "air_date": "2025-09-14",
          "episode_count": 22,
          "id": 460392,
          "name": "Сезон 2",
          "overview": "",
          "poster_path": "/sZeGoeE4pfPClCLEZHuC8ocReOw.jpg",
          "season_number": 2,
          "vote_average": 7.6
        }
      ],
      "spoken_languages": [
        {
          "english_name": "English",
          "iso_639_1": "en",
          "name": "English"
        },
        {
          "english_name": "Japanese",
          "iso_639_1": "ja",
          "name": "日本語"
        },
        {
          "english_name": "Hungarian",
          "iso_639_1": "hu",
          "name": "Magyar"
        }
      ],
      "status": "Returning Series",
      "tagline": "",
      "type": "Scripted",
      "release_quality": "",
      "media_type": "tv",
      "categories": [
        "kinozal_tv"
      ]
    },
    {
      "adult": false,
      "backdrop_path": "/ppBiYWnUn2STU8YUdlct4Klfyu4.jpg",
      "genre_ids": [
        18,
        35
      ],
      "id": 69630,
      "origin_country": [
        "US"
      ],
      "original_language": "en",
      "original_name": "The Bold Type",
      "overview": "История трёх подруг, Джейн, Кэт и Саттон, которые работают в крупном глянцевом женском журнале «Scarlet» и во всём поддерживают друг друга. Девушки живут яркой насыщенной жизнью в Нью-Йорке, ищут себя, исследуют свою сексуальность, любовь и мир моды.",
      "popularity": 13.9812,
      "poster_path": "/oSejtpBXwHoStuAkS6Wwm1e5Xyr.jpg",
      "first_air_date": "2017-06-20",
      "softcore": false,
      "name": "Жирным шрифтом",
      "vote_average": 7.7,
      "vote_count": 200,
      "created_by": [
        {
          "id": 488074,
          "credit_id": "59673f5192514121f0120cc3",
          "name": "Сара Уотсон",
          "original_name": "Sarah Watson",
          "gender": 1,
          "profile_path": null
        }
      ],
      "episode_run_time": [
        45
      ],
      "genres": [
        {
          "id": 18,
          "name": "драма"
        },
        {
          "id": 35,
          "name": "комедия"
        }
      ],
      "homepage": "http://freeform.go.com/shows/the-bold-type",
      "in_production": false,
      "languages": [
        "en"
      ],
      "last_air_date": "2021-06-30",
      "last_episode_to_air": {
        "id": 2965073,
        "name": "Эпизод 6",
        "overview": "",
        "vote_average": 1,
        "vote_count": 1,
        "air_date": "2021-06-30",
        "episode_number": 6,
        "episode_type": "finale",
        "production_code": "",
        "runtime": 43,
        "season_number": 5,
        "show_id": 69630,
        "still_path": "/jEEM3Z00t9s5FBNwaRWimR8tX1V.jpg"
      },
      "next_episode_to_air": null,
      "networks": [
        {
          "id": 1267,
          "logo_path": "/jk2Z7WH6JnHSZrxouYh4sireM3a.png",
          "name": "Freeform",
          "origin_country": "US"
        }
      ],
      "number_of_episodes": 52,
      "number_of_seasons": 5,
      "production_companies": [
        {
          "id": 52961,
          "logo_path": null,
          "name": "The District",
          "origin_country": "US"
        },
        {
          "id": 26727,
          "logo_path": "/jeTxdjXhzgKZyLr3l9MllkTn3fy.png",
          "name": "Universal Television",
          "origin_country": "US"
        }
      ],
      "production_countries": [
        {
          "iso_3166_1": "US",
          "name": "United States of America"
        }
      ],
      "seasons": [
        {
          "air_date": "2017-06-20",
          "episode_count": 10,
          "id": 83873,
          "name": "Сезон 1",
          "overview": "",
          "poster_path": "/82WbBa9668j11zJcQrEnCprs6C8.jpg",
          "season_number": 1,
          "vote_average": 7.3
        },
        {
          "air_date": "2018-06-12",
          "episode_count": 10,
          "id": 93679,
          "name": "Сезон 2",
          "overview": "",
          "poster_path": "/nBYEMgrLs3lW3Fh1yu24iZdQxny.jpg",
          "season_number": 2,
          "vote_average": 7.3
        },
        {
          "air_date": "2019-04-09",
          "episode_count": 10,
          "id": 118391,
          "name": "Сезон 3",
          "overview": "",
          "poster_path": "/hhhduh0q7qdXqVd4mJdttkPJgYa.jpg",
          "season_number": 3,
          "vote_average": 7.5
        },
        {
          "air_date": "2020-01-23",
          "episode_count": 16,
          "id": 135471,
          "name": "Сезон 4",
          "overview": "",
          "poster_path": "/9AjskJ8Y89AG5Q4erbhAuCXiw94.jpg",
          "season_number": 4,
          "vote_average": 7.7
        },
        {
          "air_date": "2021-05-26",
          "episode_count": 6,
          "id": 192392,
          "name": "Сезон 5",
          "overview": "",
          "poster_path": "/cKloQpl6zE7kdFf8SUeYU2qPT9H.jpg",
          "season_number": 5,
          "vote_average": 1
        }
      ],
      "spoken_languages": [
        {
          "english_name": "English",
          "iso_639_1": "en",
          "name": "English"
        }
      ],
      "status": "Ended",
      "tagline": "",
      "type": "Scripted",
      "release_quality": "",
      "media_type": "tv",
      "categories": [
        "kinozal_tv"
      ]
    },
    {
      "adult": false,
      "backdrop_path": "/wjs3xiJvh7h1qvIpv8kEmz79ys0.jpg",
      "genre_ids": [
        18,
        10766
      ],
      "id": 12656,
      "origin_country": [
        "MX"
      ],
      "original_language": "es",
      "original_name": "Rosalinda",
      "overview": "Двадцатью годами ранее событий, которые отражены в этой теленовелле, Соледад, чтобы защитить своего мужа Альфредо, берёт на себя вину за убийство его шурина.",
      "popularity": 7.9618,
      "poster_path": "/7GqB48FlDbyGpTFuD0tMnZ0JwLi.jpg",
      "first_air_date": "1999-03-01",
      "softcore": false,
      "name": "Розалинда",
      "vote_average": 7.1,
      "vote_count": 176,
      "created_by": [
        {
          "id": 1244061,
          "credit_id": "5258229f760ee36aaa7c8599",
          "name": "Делия Фиальо",
          "original_name": "Delia Fiallo",
          "gender": 1,
          "profile_path": "/7n7Mo61t47uHjpdk7MdfwGAPiR1.jpg"
        }
      ],
      "episode_run_time": [
        45
      ],
      "genres": [
        {
          "id": 18,
          "name": "драма"
        },
        {
          "id": 10766,
          "name": "Мыльная опера"
        }
      ],
      "homepage": "https://voyo.markiza.sk/serialy/6463-rosalinda",
      "in_production": false,
      "languages": [
        "es"
      ],
      "last_air_date": "1999-06-18",
      "last_episode_to_air": {
        "id": 1966491,
        "name": "Эпизод 80",
        "overview": "",
        "vote_average": 0,
        "vote_count": 0,
        "air_date": "1999-06-18",
        "episode_number": 80,
        "episode_type": "finale",
        "production_code": "",
        "runtime": 44,
        "season_number": 1,
        "show_id": 12656,
        "still_path": null
      },
      "next_episode_to_air": null,
      "networks": [
        {
          "id": 487,
          "logo_path": "/5Cc4MKZWQKDRRHVGVDvnYhSf3UR.png",
          "name": "Las Estrellas",
          "origin_country": "MX"
        }
      ],
      "number_of_episodes": 80,
      "number_of_seasons": 1,
      "production_companies": [
        {
          "id": 20911,
          "logo_path": "/cpeCt1KrMkj2r27JPEx3SPgTCvJ.png",
          "name": "Televisa",
          "origin_country": "MX"
        }
      ],
      "production_countries": [
        {
          "iso_3166_1": "MX",
          "name": "Mexico"
        }
      ],
      "seasons": [
        {
          "air_date": "1999-03-01",
          "episode_count": 80,
          "id": 126446,
          "name": "Сезон 1",
          "overview": "",
          "poster_path": "/tdtP6BxtggJwxGPrw3uYaRwb8Pd.jpg",
          "season_number": 1,
          "vote_average": 0
        }
      ],
      "spoken_languages": [
        {
          "english_name": "Spanish",
          "iso_639_1": "es",
          "name": "Español"
        }
      ],
      "status": "Ended",
      "tagline": "",
      "type": "Scripted",
      "release_quality": "",
      "media_type": "tv",
      "categories": [
        "kinozal_tv"
      ]
    },
    {
      "adult": false,
      "backdrop_path": "/uTWhbLc7Bj4qNSdW3ZvZKL8cOHv.jpg",
      "genre_ids": [
        10765,
        18
      ],
      "id": 125988,
      "origin_country": [
        "US"
      ],
      "original_language": "en",
      "original_name": "Silo",
      "overview": "На отравленной гибнущей планете будущего тысячи людей ютятся в огромном подземном укрытии. Нарушение шерифом основного правила и серия загадочных смертей вынуждают инженера Джульетту заняться раскрытием тайн и поиском правды о бункере.",
      "popularity": 170.0016,
      "poster_path": "/gRkvq6FgiGRdtCwhVIozaUqhoDL.jpg",
      "first_air_date": "2023-05-04",
      "softcore": false,
      "name": "Укрытие",
      "vote_average": 8.157,
      "vote_count": 2154,
      "created_by": [
        {
          "id": 21206,
          "credit_id": "6404e86a021cee00da36d3be",
          "name": "Грэм Йост",
          "original_name": "Graham Yost",
          "gender": 2,
          "profile_path": "/lFlKo3Bm9QMe7Qwhry21CEobj8d.jpg"
        }
      ],
      "episode_run_time": [],
      "genres": [
        {
          "id": 10765,
          "name": "НФ и Фэнтези"
        },
        {
          "id": 18,
          "name": "драма"
        }
      ],
      "homepage": "https://tv.apple.com/show/umc.cmc.3yksgc857px0k0rqe5zd4jice",
      "in_production": true,
      "languages": [
        "en"
      ],
      "last_air_date": "2026-07-02",
      "last_episode_to_air": {
        "id": 7173957,
        "name": "Кто ты?",
        "overview": "Новый мэр Джульетта ничего не помнит о времени, проведенном во внешнем мире, а также о своем прошлом.",
        "vote_average": 3.95,
        "vote_count": 10,
        "air_date": "2026-07-02",
        "episode_number": 1,
        "episode_type": "standard",
        "production_code": "",
        "runtime": 52,
        "season_number": 3,
        "show_id": 125988,
        "still_path": "/nIvrv95n7gukebcCEUeZJDy9iEp.jpg"
      },
      "next_episode_to_air": {
        "id": 7173958,
        "name": "Всё хорошо",
        "overview": "Биллингс расследует исчезновение. Дэниел Кин вступает в перепалку с журналисткой.",
        "vote_average": 2.8,
        "vote_count": 5,
        "air_date": "2026-07-09",
        "episode_number": 2,
        "episode_type": "standard",
        "production_code": "",
        "runtime": 52,
        "season_number": 3,
        "show_id": 125988,
        "still_path": "/u4kB03bgyjnwDEIpBkpjqTvdcbz.jpg"
      },
      "networks": [
        {
          "id": 2552,
          "logo_path": "/bngHRFi794mnMq34gfVcm9nDxN1.png",
          "name": "Apple TV",
          "origin_country": ""
        }
      ],
      "number_of_episodes": 30,
      "number_of_seasons": 3,
      "production_companies": [
        {
          "id": 23242,
          "logo_path": "/ucE6dN6pUPfZHH5JlXkq44TDUMS.png",
          "name": "AMC Studios",
          "origin_country": "US"
        },
        {
          "id": 65105,
          "logo_path": null,
          "name": "Nemofilms",
          "origin_country": "US"
        },
        {
          "id": 199363,
          "logo_path": null,
          "name": "Mimir Films",
          "origin_country": "US"
        },
        {
          "id": 194232,
          "logo_path": "/oE7H93u8sy5vvW5EH3fpCp68vvB.png",
          "name": "Apple Studios",
          "origin_country": "US"
        }
      ],
      "production_countries": [
        {
          "iso_3166_1": "US",
          "name": "United States of America"
        }
      ],
      "seasons": [
        {
          "air_date": "2023-05-04",
          "episode_count": 10,
          "id": 196076,
          "name": "Сезон 1",
          "overview": "В мрачном антиутопическом будущем человечество цепляется за выживание глубоко под землей в пределах колоссального бункера. Джульетта, инженер, которой поручено разгадать тайну смерти коллеги, раскрывает поразительные секреты, которые угрожают самой сути их замкнутого мира.",
          "poster_path": "/pVsPWmqscpvgv83ld138POqKM6p.jpg",
          "season_number": 1,
          "vote_average": 7.3
        },
        {
          "air_date": "2024-11-14",
          "episode_count": 10,
          "id": 404198,
          "name": "Сезон 2",
          "overview": "Джульетта Николс, оказавшаяся за пределами бункера с отказавшим костюмом, мчится наперегонки со временем, ошеломленная тем, что рядом находится другой бункер, который может стать ее единственной надеждой на выживание. Тем временем внутри бункера назревают беспорядки, и Бернард Холланд собирает жителей, чтобы поддержать порядок на фоне растущих вопросов об их мире. По мере того как Джульетта сталкивается с неожиданными опасностями вблизи нового силоса, начинают всплывать скрытые истины о происхождении силосов и мира за их пределами, углубляя тайну.",
          "poster_path": "/fjP8AWQWfR1gojYGCsR6XpN2Gb6.jpg",
          "season_number": 2,
          "vote_average": 6.7
        },
        {
          "air_date": "2026-07-02",
          "episode_count": 10,
          "id": 512220,
          "name": "Сезон 3",
          "overview": "Третий сезон раскрывает историю происхождения, действие которой происходит на несколько столетий раньше, одновременно продолжая сагу о дистопическом обществе из 10 000 человек, живущих под землёй при загадочных обстоятельствах. В настоящем Джульетта Николс выживает после принудительной «чистки», но возвращается с потерей памяти, пока убежище оправляется от восстания и сталкивается с новой опасной угрозой. Тем временем в «прежние времена» журналистка Хелен Дрю и конгрессмен Дэниел Кин раскрывают заговор, который втягивает их в цепь событий с катастрофическими, необратимыми последствиями.",
          "poster_path": "/gRkvq6FgiGRdtCwhVIozaUqhoDL.jpg",
          "season_number": 3,
          "vote_average": 3.4
        }
      ],
      "spoken_languages": [
        {
          "english_name": "English",
          "iso_639_1": "en",
          "name": "English"
        }
      ],
      "status": "Returning Series",
      "tagline": "Правда таится в прошлом.",
      "type": "Scripted",
      "release_quality": "2160p",
      "media_type": "tv",
      "categories": [
        "kinozal_tv"
      ]
    },
    {
      "adult": false,
      "backdrop_path": "/uYi9bmJPBGC5tI2b6K4mdsUJivK.jpg",
      "genre_ids": [
        10759,
        35,
        18
      ],
      "id": 233347,
      "origin_country": [
        "KR"
      ],
      "original_language": "ko",
      "original_name": "스터디그룹",
      "overview": "Юн Га Мин учится в печально известной профессиональной школе, где много проблемных учеников. Он выглядит образцовым студентом в очках, у которого аккуратная внешность и невинный вид. Парень мечтает хорошо учиться, но у него самые низкие оценки в школе. Недостаток академических знаний Га Мин компенсирует силой и боевыми навыками. Чтобы улучшить свои оценки, он формирует учебную группу. Всякий раз, когда члены его учебной группы попадают в беду, Юн Га Мин защищает их. На основе одноименного вебтуна.",
      "popularity": 16.1836,
      "poster_path": "/rLrEtysTwvVZESavwufnoGIaq8j.jpg",
      "first_air_date": "2025-01-23",
      "name": "Учебная группа",
      "vote_average": 8.424,
      "vote_count": 92,
      "created_by": [
        {
          "id": 1988603,
          "credit_id": "679c278e35e31dcee74d115d",
          "name": "Lee Jang-hoon",
          "original_name": "Lee Jang-hoon",
          "gender": 2,
          "profile_path": "/YttL5ivFnW7NvqTPZvOBAXyPgj.jpg"
        }
      ],
      "episode_run_time": [
        43
      ],
      "genres": [
        {
          "id": 10759,
          "name": "Боевик и Приключения"
        },
        {
          "id": 35,
          "name": "комедия"
        },
        {
          "id": 18,
          "name": "драма"
        }
      ],
      "homepage": "https://www.tving.com/contents/P001765418",
      "in_production": true,
      "languages": [
        "ko"
      ],
      "last_air_date": "2025-02-20",
      "last_episode_to_air": {
        "id": 5387985,
        "name": "Эпизод 10",
        "overview": "",
        "vote_average": 8.5,
        "vote_count": 2,
        "air_date": "2025-02-20",
        "episode_number": 10,
        "episode_type": "finale",
        "production_code": "",
        "runtime": 43,
        "season_number": 1,
        "show_id": 233347,
        "still_path": "/joXwuwU0nLfx39xkCxYJpbESVOx.jpg"
      },
      "next_episode_to_air": null,
      "networks": [
        {
          "id": 3897,
          "logo_path": "/cfMtt9sNl2bDyHuoPSZouEqDB9N.png",
          "name": "TVING",
          "origin_country": "KR"
        }
      ],
      "number_of_episodes": 10,
      "number_of_seasons": 1,
      "production_companies": [
        {
          "id": 186649,
          "logo_path": "/drUn9QIaCOsI2LMOwDjprdybHKB.png",
          "name": "YLAB",
          "origin_country": "KR"
        },
        {
          "id": 86418,
          "logo_path": "/vzzqRwqTin3iAAMw2JlrmVPNnPa.png",
          "name": "Studio Dragon",
          "origin_country": "KR"
        },
        {
          "id": 193216,
          "logo_path": "/jJfmocfyr0FD5gv8KR6pmqNXDSo.png",
          "name": "VieOn Network",
          "origin_country": "VN"
        },
        {
          "id": 253523,
          "logo_path": "/j34CGW0WlWzj7HYwPcLGzEGL5nq.png",
          "name": "DatVietVAC Group Holdings",
          "origin_country": "VN"
        }
      ],
      "production_countries": [
        {
          "iso_3166_1": "KR",
          "name": "South Korea"
        }
      ],
      "seasons": [
        {
          "air_date": "2025-01-23",
          "episode_count": 10,
          "id": 354114,
          "name": "Сезон 1",
          "overview": "",
          "poster_path": "/ibxKveIuPrAYVqBjc8UnbUNQmM1.jpg",
          "season_number": 1,
          "vote_average": 8.2
        }
      ],
      "spoken_languages": [
        {
          "english_name": "Korean",
          "iso_639_1": "ko",
          "name": "한국어/조선말"
        }
      ],
      "status": "Returning Series",
      "tagline": "",
      "type": "Scripted",
      "release_quality": "",
      "media_type": "tv",
      "categories": [
        "kinozal_tv"
      ]
    },
    {
      "adult": false,
      "backdrop_path": "/mqCjXPT60Yt4cskzy3oQyZjLKHe.jpg",
      "genre_ids": [
        18,
        80
      ],
      "id": 137883,
      "origin_country": [
        "BR"
      ],
      "original_language": "pt",
      "original_name": "Cangaço Novo",
      "overview": "Убальдо получает наследство, которое навсегда изменит его судьбу. В самом сердце северо-западной пустыни он станет предводителем стаи безжалостных бандитов, выполняя завет своего биологического отца — мифического Кангасейро.",
      "popularity": 6.8663,
      "poster_path": "/ijw2ncRKoIbJdQ9cEBHU9sVtua9.jpg",
      "first_air_date": "2023-08-17",
      "softcore": false,
      "name": "Новый кангасейро",
      "vote_average": 7.6,
      "vote_count": 62,
      "created_by": [
        {
          "id": 4267695,
          "credit_id": "650093d5ffc9de0ee176f943",
          "name": "Eduardo Melo",
          "original_name": "Eduardo Melo",
          "gender": 0,
          "profile_path": null
        },
        {
          "id": 1434198,
          "credit_id": "650093e2db4ed6103855f884",
          "name": "Mariana Bardan",
          "original_name": "Mariana Bardan",
          "gender": 0,
          "profile_path": null
        }
      ],
      "episode_run_time": [],
      "genres": [
        {
          "id": 18,
          "name": "драма"
        },
        {
          "id": 80,
          "name": "криминал"
        }
      ],
      "homepage": "https://www.primevideo.com/dp/0JTVXZMN0PQDXQT5B0OQG2D44I",
      "in_production": true,
      "languages": [
        "pt"
      ],
      "last_air_date": "2026-04-24",
      "last_episode_to_air": {
        "id": 6872433,
        "name": "Эпизод 7",
        "overview": "",
        "vote_average": 10,
        "vote_count": 1,
        "air_date": "2026-04-24",
        "episode_number": 7,
        "episode_type": "finale",
        "production_code": "",
        "runtime": 52,
        "season_number": 2,
        "show_id": 137883,
        "still_path": "/oRve4jbmVGSB7fb5SEFysDtvS7h.jpg"
      },
      "next_episode_to_air": null,
      "networks": [
        {
          "id": 1024,
          "logo_path": "/w7HfLNm9CWwRmAMU58udl2L7We7.png",
          "name": "Prime Video",
          "origin_country": ""
        }
      ],
      "number_of_episodes": 15,
      "number_of_seasons": 2,
      "production_companies": [
        {
          "id": 345,
          "logo_path": "/hj2nqoG2F9COm16fqvM0YpY3jL4.png",
          "name": "O2 Filmes",
          "origin_country": "BR"
        },
        {
          "id": 208227,
          "logo_path": "/hYREaYiVyoGVP26CbDpAWD3wDRD.png",
          "name": "Amazon Studios",
          "origin_country": "BR"
        },
        {
          "id": 56,
          "logo_path": "/cEaxANEisCqeEoRvODv2dO1I0iI.png",
          "name": "Amblin Entertainment",
          "origin_country": "US"
        },
        {
          "id": 210099,
          "logo_path": "/g5oRCNCi8kNVb8gEoSoIcqkhjmR.png",
          "name": "Amazon MGM Studios",
          "origin_country": "US"
        }
      ],
      "production_countries": [
        {
          "iso_3166_1": "BR",
          "name": "Brazil"
        }
      ],
      "seasons": [
        {
          "air_date": "2023-08-17",
          "episode_count": 8,
          "id": 218228,
          "name": "Сезон 1",
          "overview": "",
          "poster_path": "/cFxXB0WH25inmNGo7UYYGJKQq7i.jpg",
          "season_number": 1,
          "vote_average": 7.3
        },
        {
          "air_date": "2026-04-24",
          "episode_count": 7,
          "id": 379908,
          "name": "Сезон 2",
          "overview": "",
          "poster_path": "/wEmtgTyNTjLonxxazdruwcdoxiy.jpg",
          "season_number": 2,
          "vote_average": 10
        }
      ],
      "spoken_languages": [
        {
          "english_name": "Portuguese",
          "iso_639_1": "pt",
          "name": "Português"
        }
      ],
      "status": "Returning Series",
      "tagline": "",
      "type": "Scripted",
      "release_quality": "",
      "media_type": "tv",
      "categories": [
        "kinozal_tv"
      ]
    },
    {
      "adult": false,
      "backdrop_path": "/8zbAoryWbtH0DKdev8abFAjdufy.jpg",
      "genre_ids": [
        10765,
        9648,
        10759
      ],
      "id": 66732,
      "origin_country": [
        "US"
      ],
      "original_language": "en",
      "original_name": "Stranger Things",
      "overview": "1980-е годы, тихий провинциальный американский городок. Благоприятное течение местной жизни нарушает загадочное исчезновение подростка по имени Уилл. Выяснить обстоятельства дела полны решимости родные мальчика и местный шериф, также события затрагивают лучшего друга Уилла – Майка. Он начинает собственное расследование. Майк уверен, что близок к разгадке, и теперь ему предстоит оказаться в эпицентре ожесточенной битвы потусторонних сил.",
      "popularity": 1393.7498,
      "poster_path": "/uKBjtMZ7yDlJovmqIOBe0ZVGdVM.jpg",
      "first_air_date": "2016-07-15",
      "name": "Очень странные дела",
      "vote_average": 8.587,
      "vote_count": 20090,
      "created_by": [
        {
          "id": 1179422,
          "credit_id": "57599b039251410a99001cce",
          "name": "Росс Даффер",
          "original_name": "Ross Duffer",
          "gender": 2,
          "profile_path": "/mL7OS3SBZ7V2Vtuzd133YEACYc9.jpg"
        },
        {
          "id": 1179419,
          "credit_id": "57599b0e925141378a002c87",
          "name": "Мэтт Даффер",
          "original_name": "Matt Duffer",
          "gender": 2,
          "profile_path": "/kXO5CnSxC0znMAICGxnPeuGP73U.jpg"
        }
      ],
      "episode_run_time": [],
      "genres": [
        {
          "id": 10765,
          "name": "НФ и Фэнтези"
        },
        {
          "id": 9648,
          "name": "детектив"
        },
        {
          "id": 10759,
          "name": "Боевик и Приключения"
        }
      ],
      "homepage": "https://www.netflix.com/title/80057281",
      "in_production": false,
      "languages": [
        "en"
      ],
      "last_air_date": "2025-12-31",
      "last_episode_to_air": {
        "id": 5607051,
        "name": "Восьмая глава. Внешняя сторона",
        "overview": "Векна готовится разрушить привычный мир, и команде приходится рисковать всем, чтобы победить его раз и навсегда.",
        "vote_average": 7.223,
        "vote_count": 119,
        "air_date": "2025-12-31",
        "episode_number": 8,
        "episode_type": "finale",
        "production_code": "",
        "runtime": 129,
        "season_number": 5,
        "show_id": 66732,
        "still_path": "/kP23RWbUWM6vGhT9PxFyP5VT3y4.jpg"
      },
      "next_episode_to_air": null,
      "networks": [
        {
          "id": 213,
          "logo_path": "/wwemzKWzjKYJFfCeiB57q3r4Bcm.png",
          "name": "Netflix",
          "origin_country": ""
        }
      ],
      "number_of_episodes": 42,
      "number_of_seasons": 5,
      "production_companies": [
        {
          "id": 2575,
          "logo_path": "/9YJrHYlcfHtwtulkFMAies3aFEl.png",
          "name": "21 Laps Entertainment",
          "origin_country": "US"
        },
        {
          "id": 170090,
          "logo_path": null,
          "name": "Monkey Massacre Productions",
          "origin_country": "US"
        },
        {
          "id": 184664,
          "logo_path": "/4qv40ryAKUzvwptbv13eXUAl1Wm.png",
          "name": "Upside Down Pictures",
          "origin_country": "US"
        }
      ],
      "production_countries": [
        {
          "iso_3166_1": "US",
          "name": "United States of America"
        }
      ],
      "seasons": [
        {
          "air_date": "2016-07-15",
          "episode_count": 8,
          "id": 77680,
          "name": "Очень странные дела",
          "overview": "Главное действие сериала разворачивается в 80-х годах на территории тихого провинциального города. Благоприятное течение местной жизни нарушает загадочное исчезновение подростка по имени Уилл. Выяснить обстоятельства дела, полны решимости родные мальчика и местный шериф. Также события затрагивают лучшего друга Уилла — Майка. Он начинает собственное расследование. Теперь Майк уверен, что близок к разгадке, однако для этого ему предстоит оказаться в эпицентре ожесточённой битвы потусторонних сил.",
          "poster_path": "/uKBjtMZ7yDlJovmqIOBe0ZVGdVM.jpg",
          "season_number": 1,
          "vote_average": 8.4
        },
        {
          "air_date": "2017-10-27",
          "episode_count": 9,
          "id": 83248,
          "name": "Очень странные дела 2",
          "overview": "Прошел уже почти год со дня странного исчезновения Уилла. Но жизнь в Хоукинсе так и не стала прежней. Совсем.",
          "poster_path": "/hrsRj7bJj2OrfuuujuvaJS020wp.jpg",
          "season_number": 2,
          "vote_average": 8.2
        },
        {
          "air_date": "2019-07-04",
          "episode_count": 8,
          "id": 115216,
          "name": "Очень странные дела 3",
          "overview": "Зарождающийся роман. Новый торговый центр. Нашествие бешеных крыс. На дворе 1985 год, в Хоукинсе лето... способное изменить все навсегда.",
          "poster_path": "/4tUKTw2vvFTvYgdMpYBJbXU8etk.jpg",
          "season_number": 3,
          "vote_average": 8.1
        },
        {
          "air_date": "2022-05-27",
          "episode_count": 9,
          "id": 163313,
          "name": "Очень странные дела 4",
          "overview": "Тьма возвращается в Хоукинс как раз к весенним каникулам. С ней приходят тревожные воспоминания, новый ужас и очередная зловещая угроза.",
          "poster_path": "/gpDHA8vwSZ1J9aoCAVoM3HF0Wwp.jpg",
          "season_number": 4,
          "vote_average": 8.5
        },
        {
          "air_date": "2025-11-26",
          "episode_count": 8,
          "id": 402292,
          "name": "Очень странные дела 5",
          "overview": "Осень 1987 года. Хокинс потрясён открытием Разломов, и наши герои объединены одной целью: найти и убить Векну. Но он исчез — его местонахождение и планы неизвестны. Чтобы усложнить их миссию, правительство ввело в городе военный карантин и усилило охоту на Одиннадцать, вынудив её снова скрываться. С приближением годовщины исчезновения Уилла нарастает тяжёлый, знакомый страх. Надвигается последняя битва, а вместе с ней и тьма, более могущественная и смертоносная, чем всё, с чем они сталкивались прежде. Чтобы положить конец этому кошмару, им нужно, чтобы все — вся группа — объединились в последний раз.",
          "poster_path": "/eHz1SVmSoWz4YO0lDr7fir0noRd.jpg",
          "season_number": 5,
          "vote_average": 7.5
        }
      ],
      "spoken_languages": [
        {
          "english_name": "English",
          "iso_639_1": "en",
          "name": "English"
        }
      ],
      "status": "Ended",
      "tagline": "Мир переворачивается с ног на голову",
      "type": "Scripted",
      "release_quality": "2160p",
      "media_type": "tv",
      "categories": [
        "kinozal_tv"
      ]
    },
    {
      "adult": false,
      "backdrop_path": "/znA4DO7RhBNUsOcEuT3jG8EA7gX.jpg",
      "genre_ids": [
        18,
        10759,
        10768
      ],
      "id": 69557,
      "origin_country": [
        "IL"
      ],
      "original_language": "he",
      "original_name": "פאודה",
      "overview": "Драма об израильско-палестинском конфликте, который представлен на этот раз с двух сторон – еврейской и арабской, и настолько близко к реальности, насколько это возможно в кино. В центре истории - бойцы секретного подразделения \"мистаравим\", действующие на территориях под маской \"местных\" во время охоты на террористов. Спецназовцы охотятся за террористом Хамедом, которому все время удается уходить от преследования. Израильские бойцы находятся в состоянии постоянного стресса, поскольку в любую секунду ситуация может выйти из-под контроля и превратится в \"фауду\" - хаос на вражеской территории. Цена ошибки высока. Но есть цель, ради которой бойцы идут на эту тяжелую мужскую работу... \"Этот фильм - дань уважения тем, чья работа позволяет нам ночью спокойно спать.\" - Асаф Берштейн",
      "popularity": 22.6226,
      "poster_path": "/taxQfYM8zmy9Gc6qNYUnjr8xwKs.jpg",
      "first_air_date": "2015-02-15",
      "softcore": false,
      "name": "Фауда",
      "vote_average": 7.5,
      "vote_count": 249,
      "created_by": [
        {
          "id": 1744805,
          "credit_id": "58885223c3a368413b00451c",
          "name": "אבי יששכרוף",
          "original_name": "אבי יששכרוף",
          "gender": 0,
          "profile_path": null
        },
        {
          "id": 1259880,
          "credit_id": "5888524cc3a36859f300ad87",
          "name": "ליאור רז",
          "original_name": "ליאור רז",
          "gender": 2,
          "profile_path": "/bl3KLFUQ4Q0zC9lCU4qP1Jf4qHS.jpg"
        }
      ],
      "episode_run_time": [
        43
      ],
      "genres": [
        {
          "id": 18,
          "name": "драма"
        },
        {
          "id": 10759,
          "name": "Боевик и Приключения"
        },
        {
          "id": 10768,
          "name": "Война и Политика"
        }
      ],
      "homepage": "https://www.yesstudios.tv/fauda",
      "in_production": true,
      "languages": [
        "ar",
        "en",
        "he"
      ],
      "last_air_date": "2026-05-18",
      "last_episode_to_air": {
        "id": 7293374,
        "name": "Эпизод 2",
        "overview": "",
        "vote_average": 0,
        "vote_count": 0,
        "air_date": "2026-05-18",
        "episode_number": 2,
        "episode_type": "standard",
        "production_code": "",
        "runtime": 53,
        "season_number": 5,
        "show_id": 69557,
        "still_path": null
      },
      "next_episode_to_air": {
        "id": 7293415,
        "name": "Эпизод 3",
        "overview": "",
        "vote_average": 0,
        "vote_count": 0,
        "air_date": "2026-05-25",
        "episode_number": 3,
        "episode_type": "standard",
        "production_code": "",
        "runtime": null,
        "season_number": 5,
        "show_id": 69557,
        "still_path": null
      },
      "networks": [
        {
          "id": 644,
          "logo_path": "/9yWETECjfnsxZ9UtviBZXaZ087k.png",
          "name": "yes",
          "origin_country": "IL"
        }
      ],
      "number_of_episodes": 59,
      "number_of_seasons": 5,
      "production_companies": [
        {
          "id": 138116,
          "logo_path": null,
          "name": "L.Benasuly Productions",
          "origin_country": ""
        },
        {
          "id": 33244,
          "logo_path": "/kNQbbo0UaSrHVF3RjPWgXnUs00g.png",
          "name": "yes",
          "origin_country": "IL"
        },
        {
          "id": 116158,
          "logo_path": null,
          "name": "Tender Productions",
          "origin_country": "IL"
        }
      ],
      "production_countries": [
        {
          "iso_3166_1": "IL",
          "name": "Israel"
        },
        {
          "iso_3166_1": "US",
          "name": "United States of America"
        }
      ],
      "seasons": [
        {
          "air_date": null,
          "episode_count": 6,
          "id": 203218,
          "name": "Спецматериалы",
          "overview": "",
          "poster_path": null,
          "season_number": 0,
          "vote_average": 0
        },
        {
          "air_date": "2015-02-15",
          "episode_count": 12,
          "id": 83738,
          "name": "Сезон 1",
          "overview": "",
          "poster_path": "/qaaHwvdXHVRDyAQoOo4ZmGI7moJ.jpg",
          "season_number": 1,
          "vote_average": 8
        },
        {
          "air_date": "2017-12-31",
          "episode_count": 12,
          "id": 97239,
          "name": "Сезон 2",
          "overview": "",
          "poster_path": "/fJKVqLNcGZ2hYNIZYztrAKFFbJk.jpg",
          "season_number": 2,
          "vote_average": 8.1
        },
        {
          "air_date": "2019-12-26",
          "episode_count": 12,
          "id": 139093,
          "name": "Сезон 3",
          "overview": "",
          "poster_path": "/nyXjzcgVuFS6PkufotcjzGmGn4A.jpg",
          "season_number": 3,
          "vote_average": 8.2
        },
        {
          "air_date": "2022-07-13",
          "episode_count": 12,
          "id": 300425,
          "name": "Сезон 4",
          "overview": "",
          "poster_path": "/cBDCVFaVtmbBPQBKB3niq0O7spp.jpg",
          "season_number": 4,
          "vote_average": 8
        },
        {
          "air_date": "2026-05-18",
          "episode_count": 11,
          "id": 361926,
          "name": "Сезон 5",
          "overview": "",
          "poster_path": "/gFZRYXOqkLghusADQ5ju2Clyy41.jpg",
          "season_number": 5,
          "vote_average": 0
        }
      ],
      "spoken_languages": [
        {
          "english_name": "Arabic",
          "iso_639_1": "ar",
          "name": "العربية"
        },
        {
          "english_name": "English",
          "iso_639_1": "en",
          "name": "English"
        },
        {
          "english_name": "Hebrew",
          "iso_639_1": "he",
          "name": "עִבְרִית"
        }
      ],
      "status": "Returning Series",
      "tagline": "",
      "type": "Scripted",
      "release_quality": "2160p",
      "media_type": "tv",
      "categories": [
        "kinozal_tv"
      ]
    },
    {
      "adult": false,
      "backdrop_path": "/ewlmL0nxo2lLqBj69upgp2gjHpV.jpg",
      "genre_ids": [
        37,
        18
      ],
      "id": 299167,
      "origin_country": [
        "US"
      ],
      "original_language": "en",
      "original_name": "Dutton Ranch",
      "overview": "Ранчо Даттонов - дом Бет и Рипа, стало символом той жизни, о которой они мечтали, за которую отчаянно боролись и ради которой едва не пожертвовали всем. Они всей душой привязались к своей земле площадью 7000 акров, превратив её в место, которое готовы защищать любой ценой. Даже в самые тяжёлые времена Бет и Рип делают всё возможное, чтобы выстоять, сохранить своё ранчо и обеспечить достойное будущее себе и своему приёмному сыну Картеру.",
      "popularity": 56.941,
      "poster_path": "/mmxsx98NnY56CvataUqM1ktt14O.jpg",
      "first_air_date": "2026-05-15",
      "softcore": false,
      "name": "Ранчо Даттонов",
      "vote_average": 9.6,
      "vote_count": 14,
      "created_by": [
        {
          "id": 56665,
          "credit_id": "69b657aa482d00725c3b9286",
          "name": "Chad Feehan",
          "original_name": "Chad Feehan",
          "gender": 2,
          "profile_path": "/kO7cUR8nd6Fn01OYkgpEuYKYfUb.jpg"
        }
      ],
      "episode_run_time": [],
      "genres": [
        {
          "id": 37,
          "name": "вестерн"
        },
        {
          "id": 18,
          "name": "драма"
        }
      ],
      "homepage": "https://www.paramountplus.com/shows/dutton-ranch",
      "in_production": true,
      "languages": [
        "en",
        "es",
        "de"
      ],
      "last_air_date": "2026-05-15",
      "last_episode_to_air": {
        "id": 7041210,
        "name": "Эпизод 2",
        "overview": "",
        "vote_average": 9.2,
        "vote_count": 5,
        "air_date": "2026-05-15",
        "episode_number": 2,
        "episode_type": "standard",
        "production_code": "",
        "runtime": 47,
        "season_number": 1,
        "show_id": 299167,
        "still_path": "/zXO11LCZeFBjBhnSAK9zlzEsJxu.jpg"
      },
      "next_episode_to_air": {
        "id": 7041212,
        "name": "Эпизод 3",
        "overview": "",
        "vote_average": 0,
        "vote_count": 0,
        "air_date": "2026-05-22",
        "episode_number": 3,
        "episode_type": "standard",
        "production_code": "",
        "runtime": null,
        "season_number": 1,
        "show_id": 299167,
        "still_path": null
      },
      "networks": [
        {
          "id": 2076,
          "logo_path": "/4knr4ozp2IQrA3SMQlLSYKcM3ML.png",
          "name": "Paramount Network",
          "origin_country": "US"
        },
        {
          "id": 4330,
          "logo_path": "/fi83B1oztoS47xxcemFdPMhIzK.png",
          "name": "Paramount+",
          "origin_country": "US"
        }
      ],
      "number_of_episodes": 9,
      "number_of_seasons": 1,
      "production_companies": [
        {
          "id": 270146,
          "logo_path": "/4r6rIxegOrrVeJwqRxpzNrCRQMD.png",
          "name": "Paramount Television Studios",
          "origin_country": "US"
        },
        {
          "id": 124254,
          "logo_path": "/Aq2pCS1mXg4AiVwLTkh4bhcejmt.png",
          "name": "101 Studios",
          "origin_country": "US"
        },
        {
          "id": 106789,
          "logo_path": "/oEgUdRh5YWF6Il705WnpwauirIj.png",
          "name": "Bosque Ranch Productions",
          "origin_country": "US"
        },
        {
          "id": 4700,
          "logo_path": "/A32wmjrs9Psf4zw0uaixF0GXfxq.png",
          "name": "Linson Entertainment",
          "origin_country": "US"
        }
      ],
      "production_countries": [
        {
          "iso_3166_1": "US",
          "name": "United States of America"
        }
      ],
      "seasons": [
        {
          "air_date": "2026-05-15",
          "episode_count": 9,
          "id": 471596,
          "name": "Сезон 1",
          "overview": "",
          "poster_path": "/xsiecCxd8lkcAluw0wWwbW5CwSv.jpg",
          "season_number": 1,
          "vote_average": 9.3
        }
      ],
      "spoken_languages": [
        {
          "english_name": "English",
          "iso_639_1": "en",
          "name": "English"
        },
        {
          "english_name": "Spanish",
          "iso_639_1": "es",
          "name": "Español"
        },
        {
          "english_name": "German",
          "iso_639_1": "de",
          "name": "Deutsch"
        }
      ],
      "status": "Returning Series",
      "tagline": "",
      "type": "Scripted",
      "release_quality": "2160p",
      "media_type": "tv",
      "categories": [
        "kinozal_tv"
      ]
    },
    {
      "adult": false,
      "backdrop_path": "/6Fbrrf2jaYJ8s3nnnuhhvvDjTZN.jpg",
      "genre_ids": [
        35
      ],
      "id": 295780,
      "origin_country": [
        "US"
      ],
      "original_language": "en",
      "original_name": "Life, Larry and the Pursuit of Unhappiness: An Almost History of America",
      "overview": "Ларри Дэвид - вечно недовольный и хронически неудачливый мужчина - по иронии судьбы оказывается в эпицентре ключевых событий прошлого. Компанию ему составят бывший президент США Барак Обама и его жена Мишель.",
      "popularity": 25.5605,
      "poster_path": "/eA8lwlHAuFQrZzek25xgGZCgImu.jpg",
      "first_air_date": "2026-06-26",
      "softcore": false,
      "name": "Жизнь, Ларри и стремление к несчастью: Почти история Америки",
      "vote_average": 5.2,
      "vote_count": 10,
      "created_by": [
        {
          "id": 16376,
          "credit_id": "693c7ad68b3a74d4baf77f6e",
          "name": "Ларри Дэвид",
          "original_name": "Larry David",
          "gender": 2,
          "profile_path": "/ojPx93eaDcanOVi4AH14uAFwXhn.jpg"
        },
        {
          "id": 57405,
          "credit_id": "6a3f6018bf471b6e3d3cce76",
          "name": "Джефф Шеффер",
          "original_name": "Jeff Schaffer",
          "gender": 2,
          "profile_path": "/zjGUb5c4k6UiM3lyOwNk7GS04ED.jpg"
        }
      ],
      "episode_run_time": [],
      "genres": [
        {
          "id": 35,
          "name": "комедия"
        }
      ],
      "homepage": "https://www.hbo.com/content/life-larry-and-the-pursuit-of-unhappiness",
      "in_production": true,
      "languages": [
        "en"
      ],
      "last_air_date": "2026-07-03",
      "last_episode_to_air": {
        "id": 7037406,
        "name": "Эпизод 2",
        "overview": "",
        "vote_average": 0,
        "vote_count": 0,
        "air_date": "2026-07-03",
        "episode_number": 2,
        "episode_type": "standard",
        "production_code": "",
        "runtime": 32,
        "season_number": 1,
        "show_id": 295780,
        "still_path": "/nnmKTDEbcSkCybBrDdOkcbwLwtF.jpg"
      },
      "next_episode_to_air": {
        "id": 7037407,
        "name": "Эпизод 3",
        "overview": "",
        "vote_average": 0,
        "vote_count": 0,
        "air_date": "2026-07-10",
        "episode_number": 3,
        "episode_type": "standard",
        "production_code": "",
        "runtime": null,
        "season_number": 1,
        "show_id": 295780,
        "still_path": null
      },
      "networks": [
        {
          "id": 49,
          "logo_path": "/tuomPhY2UtuPTqqFnKMVHvSb724.png",
          "name": "HBO",
          "origin_country": "US"
        }
      ],
      "number_of_episodes": 7,
      "number_of_seasons": 1,
      "production_companies": [
        {
          "id": 122147,
          "logo_path": "/eotra9uY7zyivEzDL4bFdn7Elm4.png",
          "name": "Higher Ground",
          "origin_country": "US"
        },
        {
          "id": 3268,
          "logo_path": "/tuomPhY2UtuPTqqFnKMVHvSb724.png",
          "name": "HBO",
          "origin_country": "US"
        }
      ],
      "production_countries": [
        {
          "iso_3166_1": "US",
          "name": "United States of America"
        }
      ],
      "seasons": [
        {
          "air_date": "2026-06-26",
          "episode_count": 7,
          "id": 464822,
          "name": "Сезон 1",
          "overview": "",
          "poster_path": "/eA8lwlHAuFQrZzek25xgGZCgImu.jpg",
          "season_number": 1,
          "vote_average": 2.5
        }
      ],
      "spoken_languages": [
        {
          "english_name": "English",
          "iso_639_1": "en",
          "name": "English"
        }
      ],
      "status": "Returning Series",
      "tagline": "",
      "type": "Miniseries",
      "release_quality": "2160p",
      "media_type": "tv",
      "categories": [
        "kinozal_tv"
      ]
    },
    {
      "adult": false,
      "backdrop_path": "/2yDDwP48GqL9Fpb6UEgGHyqM63y.jpg",
      "genre_ids": [
        18,
        9648,
        80
      ],
      "id": 278178,
      "origin_country": [
        "US"
      ],
      "original_language": "en",
      "original_name": "I Will Find You",
      "overview": "Отец, несправедливо осужденный за убийство сына, отбывает срок в тюрьме. Узнав, что мальчик еще может быть жив, герой предпринимает отчаянные шаги, стремясь его спасти.",
      "popularity": 6.9228,
      "poster_path": "/tz1msIMyN5IAl2W4C0JBsjIadPj.jpg",
      "first_air_date": "2026-06-18",
      "softcore": false,
      "name": "Я тебя отыщу",
      "vote_average": 10,
      "vote_count": 1,
      "created_by": [
        {
          "id": 1232167,
          "credit_id": "6746095bc24765fa2f2e18f8",
          "name": "Robert Hull",
          "original_name": "Robert Hull",
          "gender": 2,
          "profile_path": "/tvL8qh4l1HQpY74ce9Xoha7KHeX.jpg"
        }
      ],
      "episode_run_time": [],
      "genres": [
        {
          "id": 18,
          "name": "драма"
        },
        {
          "id": 9648,
          "name": "детектив"
        },
        {
          "id": 80,
          "name": "криминал"
        }
      ],
      "homepage": "https://www.netflix.com/title/81509368",
      "in_production": false,
      "languages": [
        "en"
      ],
      "last_air_date": null,
      "last_episode_to_air": null,
      "next_episode_to_air": {
        "id": 6343846,
        "name": "1 эпизод",
        "overview": "Дэвид Берроуз отбывает в тюрьме срок за убийство, которого не совершал. Узнав ошеломительную новость о том, что его сын еще может быть жив, герой решается на побег.",
        "vote_average": 0,
        "vote_count": 0,
        "air_date": "2026-06-18",
        "episode_number": 1,
        "episode_type": "standard",
        "production_code": "",
        "runtime": 47,
        "season_number": 1,
        "show_id": 278178,
        "still_path": "/tDUUexyRzcPrjNaz9sZfcdnYTgS.jpg"
      },
      "networks": [
        {
          "id": 213,
          "logo_path": "/wwemzKWzjKYJFfCeiB57q3r4Bcm.png",
          "name": "Netflix",
          "origin_country": ""
        }
      ],
      "number_of_episodes": 8,
      "number_of_seasons": 1,
      "production_companies": [
        {
          "id": 208514,
          "logo_path": "/4CiIJO7QTquUWkw2gyLvRyk0ds2.png",
          "name": "Final Twist Productions",
          "origin_country": "US"
        },
        {
          "id": 301948,
          "logo_path": null,
          "name": "Story Math",
          "origin_country": "US"
        }
      ],
      "production_countries": [
        {
          "iso_3166_1": "US",
          "name": "United States of America"
        }
      ],
      "seasons": [
        {
          "air_date": "2026-06-18",
          "episode_count": 8,
          "id": 430534,
          "name": "Мини-сериал",
          "overview": "",
          "poster_path": "/pb9oYHHNzauiCQZT03MpDAg46GI.jpg",
          "season_number": 1,
          "vote_average": 0
        }
      ],
      "spoken_languages": [
        {
          "english_name": "English",
          "iso_639_1": "en",
          "name": "English"
        }
      ],
      "status": "Ended",
      "tagline": "",
      "type": "Miniseries",
      "release_quality": "2160p",
      "media_type": "tv",
      "categories": [
        "kinozal_tv"
      ]
    }
  ]
}